{"ocr_results":[{"text":"厦门大学1976年各系、专业、","box":[[581,508],[1481,508],[1481,569],[581,569]]},{"text":"教研室设量情况","box":[[800,621],[1291,621],[1291,679],[800,679]]},{"text":"中文系：设汉语言文学专业，文学、语言写作教研室。","box":[[393,805],[1673,800],[1674,850],[393,855]]},{"text":"外语系：设英语，俄语、日语专业，英语、俄语、日语、公","box":[[388,896],[1807,892],[1808,945],[388,949]]},{"text":"共英语教研室。","box":[[280,992],[640,992],[640,1038],[280,1038]]},{"text":"历史系：设历史、考古专业，中国史、世界史、考古教研","box":[[391,1082],[1804,1082],[1804,1131],[391,1131]]},{"text":"室。","box":[[272,1166],[361,1169],[358,1234],[270,1231]]},{"text":"经济系：设政治经济学、计划统计、财务会计、财政金融、","box":[[388,1268],[1774,1265],[1774,1315],[388,1318]]},{"text":"对外贸易专业，政经、计统、财会、财金、外贸教研室。","box":[[280,1361],[1615,1360],[1615,1410],[280,1411]]},{"text":"数学系：设数学、控制理论专业，数学、控制理论、公共高","box":[[386,1454],[1803,1452],[1803,1504],[386,1507]]},{"text":"等数学教研室。","box":[[278,1545],[632,1548],[631,1599],[278,1596]]},{"text":"物理系：设物理学、无线电物理、半导体物理，光电子学专","box":[[387,1637],[1799,1638],[1799,1689],[387,1687]]},{"text":"业，无线电物理、半导体物理、光电子物理、公共物理、基础物","box":[[276,1732],[1798,1729],[1798,1778],[277,1781]]},{"text":"理教研室。","box":[[271,1821],[516,1818],[516,1874],[272,1877]]},{"text":"化学系，设催化化学、电化学、分析化学、高分子化学，无","box":[[383,1916],[1800,1916],[1800,1968],[383,1968]]},{"text":"机化学专业，催化化学、电化学、分析化学、高分子化学、无机化","box":[[274,2010],[1798,2013],[1798,2058],[274,2055]]},{"text":"学教研室。","box":[[274,2101],[520,2097],[521,2152],[275,2156]]},{"text":"生物系：设微生物、动物遗传育种学、植物学、寄生虫学专","box":[[382,2193],[1800,2194],[1800,2248],[382,2247]]},{"text":"业，微生物学、动物学、植物生物学、生物化学、寄生虫教研","box":[[273,2286],[1800,2290],[1800,2340],[273,2336]]},{"text":"室。","box":[[272,2375],[359,2375],[359,2435],[272,2435]]},{"text":"海洋系：设海洋化学、海洋生物、水声专业，海化、海生、","box":[[381,2473],[1771,2478],[1771,2528],[381,2523]]},{"text":"水声教研室。","box":[[272,2566],[569,2566],[569,2616],[272,2616]]},{"text":"哲学系：设哲学专业，马列主义教研室及原理原著、欧州哲","box":[[380,2656],[1792,2661],[1791,2715],[380,2710]]},{"text":"学史、中国哲学史，国际共运史四个教研组。","box":[[277,2749],[1327,2751],[1327,2805],[276,2803]]},{"text":"52","box":[[328,2837],[387,2837],[387,2894],[328,2894]]}],"dimensions":{"height":3063,"width":2084}}