{"ocr_results":[{"text":"浙江省文化大革命大事记","box":[[182,144],[599,146],[599,173],[182,171]]},{"text":"第一副主任：陈励耘","box":[[242,243],[522,246],[521,276],[241,273]]},{"text":"副主任：熊应堂、周建人、赖可可、王子达、张永生、","box":[[240,294],[1047,297],[1047,327],[239,324]]},{"text":"华银凤和一位革命工人代表为副主任。","box":[[179,346],[690,348],[689,375],[179,372]]},{"text":"常","box":[[237,393],[285,393],[285,425],[237,425]]},{"text":"委：郭志松、贺贤春、谢志明、蒋宝娣、叶仁德、","box":[[366,396],[1046,398],[1046,425],[366,423]]},{"text":"颜贻欢、.李显通、孙宏兴、翁森鹤、方剑文、滕铸、莫显耀、张来","box":[[179,444],[1067,444],[1067,477],[179,477]]},{"text":"根、沈策、王子达、马向光、邓清河、朱全林、孟昭玉、白宗善、","box":[[177,494],[1051,494],[1051,527],[177,527]]},{"text":"阮贤榜、戴克林、曹思明、王学清、刘友法。","box":[[179,545],[785,547],[785,574],[179,572]]},{"text":"3月19日","box":[[240,596],[392,596],[392,623],[240,623]]},{"text":"浙江省赴京汇报代表团胜利返回杭州。","box":[[384,594],[904,598],[904,625],[383,620]]},{"text":"3月20日浙江省军管会举行我省“赴京汇报代表团”传达报","box":[[239,643],[1061,643],[1061,673],[239,673]]},{"text":"告广播大会。南萍同志在会上作了传达报告。共三部分。","box":[[178,692],[941,694],[941,722],[178,720]]},{"text":"（一)赴京汇报的简单情况。","box":[[241,744],[585,744],[585,768],[241,768]]},{"text":"(二)中央首长的重要指示：关于当前形势；关于革命大联合问","box":[[240,790],[1062,789],[1062,819],[240,820]]},{"text":"题；关于促进革命三结合，尽快建立省革委会的问题；关于深人开","box":[[178,841],[1062,841],[1062,868],[178,868]]},{"text":"展革命大批判，搞好本单位斗、批、改问题；关于拥军爱民，提高","box":[[179,889],[1062,889],[1062,916],[179,916]]},{"text":"革命警惕的问题；关于节约闹革命问题；关于作风问题等7个问","box":[[177,937],[1061,936],[1061,963],[177,964]]},{"text":"题。","box":[[173,985],[245,985],[245,1018],[173,1018]]},{"text":"（三)如何贯彻执行中央首长的指示，南萍同志提出7条意见。","box":[[240,1036],[1041,1035],[1041,1062],[240,1063]]},{"text":"3月22日《人民日报》、《解放军报》发表《无限忠于毛主","box":[[237,1085],[1062,1081],[1062,1111],[238,1115]]},{"text":"席，团结支左立新功一人民解放军驻浙三军部队团结支左的先进事","box":[[176,1133],[1064,1132],[1064,1162],[176,1163]]},{"text":"迹》的文章。","box":[[174,1180],[348,1180],[348,1211],[174,1211]]},{"text":"3月23日","box":[[238,1232],[400,1232],[400,1260],[238,1260]]},{"text":"《浙江日报》报道了：“打倒派性，增强党性，紧","box":[[392,1230],[1064,1234],[1064,1262],[391,1258]]},{"text":"跟毛主席伟大战略部署，全省县、市革命大联合、三结合一浪高过","box":[[177,1278],[1066,1282],[1066,1312],[177,1308]]},{"text":"一浪”的通讯。","box":[[174,1327],[373,1330],[372,1361],[174,1357]]},{"text":"3月24日浙江省革命委员会胜利诞生。省市30余万军民在少","box":[[239,1379],[1065,1383],[1065,1409],[238,1406]]},{"text":"年宫广场举行隆重集会，最热烈地庆祝浙江省革命委员会成立。会","box":[[175,1427],[1067,1430],[1067,1461],[175,1458]]},{"text":"后举行隆重的庆祝游行。张春桥、许世友同志出席大会并讲了话。","box":[[176,1477],[1050,1480],[1050,1511],[176,1508]]},{"text":"王洪文代表上海市、山东省、江西省、安徽省代表团讲了话。","box":[[179,1528],[1007,1529],[1006,1559],[179,1558]]},{"text":"同日，发表了《浙江省革命委员会通告》。","box":[[242,1580],[814,1580],[814,1607],[242,1607]]},{"text":"—184—","box":[[202,1649],[342,1654],[341,1685],[201,1680]]}],"dimensions":{"height":1753,"width":1240}}