{"ocr_results":[{"text":"浙江省文化大革命大事记","box":[[240,153],[631,150],[631,175],[241,178]]},{"text":"是否看准了？”“你们有底，我们工作组也有底”，“现在还不是","box":[[236,245],[1078,249],[1078,286],[235,282]]},{"text":"我们说话的时候”等等。以要“秋后算帐”对革命师生进行威胁。","box":[[237,300],[1060,299],[1060,329],[237,330]]},{"text":"（见《省联总大事记》）","box":[[252,352],[542,351],[543,377],[252,379]]},{"text":"6月28日刘少奇、邓小平以中央名义批发中南局《关于文化","box":[[293,400],[1073,399],[1073,426],[293,427]]},{"text":"大革命的情况和意见的报告》，要各省市向宣传、教育、文化、新","box":[[237,451],[1075,448],[1075,475],[238,478]]},{"text":"闻、广插、出版等部门和所属单位派强有力的工作组，并“指示","box":[[236,500],[1053,497],[1053,525],[237,528]]},{"text":"各单位，“在牛鬼蛇神纷纷出笼，开始攻击我们的时候，不要急于","box":[[238,549],[1072,548],[1072,575],[238,576]]},{"text":"反击，要告诉革命左派，要硬着头皮顶住，领导上要善于掌握火","box":[[237,599],[1069,597],[1069,623],[238,626]]},{"text":"候，等到牛鬼蛇神大部分暴露了，就及时组织反击。”","box":[[237,646],[939,642],[939,673],[238,677]]},{"text":"同日，根据刘少奇、邓小平制订的，以中共中央名义转发的","box":[[296,696],[1069,695],[1069,722],[296,723]]},{"text":"“八条指示”的精神，江华马上提出全省党政机关的运动要“分期","box":[[255,745],[1072,745],[1072,772],[255,772]]},{"text":"分批”进行，“大字报不提倡，不组织，也不反对”，但也“不能","box":[[238,794],[1072,793],[1072,821],[238,822]]},{"text":"上街”，要“内外有别”。江华代表省委强调提出要发挥党的领导","box":[[238,845],[1071,841],[1071,867],[239,872]]},{"text":"作用。并将这个指示迅速向全省贯彻。","box":[[241,893],[718,891],[718,919],[242,921]]},{"text":"同日，江华、李丰平、陈冰等人，为了稳住杭州，他们分别约","box":[[298,942],[1068,939],[1068,967],[298,970]]},{"text":"见杭州市委有关领导谈“文化大革命”的部署问题，强调指出：杭","box":[[241,992],[1072,989],[1072,1016],[242,1019]]},{"text":"州市要全面部署，一定要分期分批、有计划、有步骤地进行，要根","box":[[239,1041],[1072,1037],[1072,1066],[240,1070]]},{"text":"据各系统、各单位的具体情况，作具体的研究部署。机关就可以收","box":[[239,1091],[1070,1088],[1070,1115],[240,1118]]},{"text":"一收，一些机密不能泄露，公安人员不能上街。武器弹药库要严密","box":[[238,1137],[1070,1135],[1070,1165],[239,1167]]},{"text":"保管、报纸、广播电台等无产阶级专政工具，决不能让坏人利用，","box":[[240,1188],[1057,1186],[1057,1214],[240,1216]]},{"text":"要求杭州市委严密控制等等。妄图以此稳住阵脚，压制全省的文化","box":[[239,1238],[1069,1238],[1069,1265],[239,1265]]},{"text":"大革命群众运动。（见《省联总大事记》）","box":[[238,1288],[778,1286],[778,1313],[239,1315]]},{"text":"同日，浙江大学1861名师生联名给毛主席、党中央发电报，控","box":[[295,1335],[1072,1336],[1072,1366],[295,1365]]},{"text":"告省委工作组压制群众运动，要求撤销工作组。并要求省委转给党","box":[[238,1385],[1072,1385],[1072,1415],[238,1415]]},{"text":"中央和毛主席，该电报被江华扣压。（见《浙江文革纪事》)","box":[[238,1434],[1025,1434],[1025,1464],[238,1464]]},{"text":"6月下旬在北京，一场规模巨大的“反干扰”运动开始了，","box":[[293,1482],[1058,1482],[1058,1515],[293,1515]]},{"text":"刘少奇和邓小平及其派出的工作组向革命造反派大举开始镇压，据","box":[[238,1533],[1072,1533],[1072,1563],[238,1563]]},{"text":"统计：在首都24所高等院校里，工作组把10211个革命小将打成","box":[[237,1582],[1072,1582],[1072,1615],[237,1615]]},{"text":"—22一","box":[[259,1653],[376,1653],[376,1688],[259,1688]]}],"dimensions":{"height":1753,"width":1240}}