{"ocr_results":[{"text":"第一阶段炮打司令部","box":[[760,144],[1067,144],[1067,171],[760,171]]},{"text":"浙江大学工作组公开说：“反对工作组就是反对省委，反对省","box":[[248,247],[1063,248],[1063,275],[248,274]]},{"text":"委就是反党，就是牛鬼蛇神，就要‘横扫’”等，继续对革命师生","box":[[188,296],[1065,296],[1065,323],[188,323]]},{"text":"进行围剿和压制。但是，遭到广大师生的强烈反对。省委为了继续","box":[[189,347],[1065,347],[1065,371],[189,371]]},{"text":"压制群众运动，竟通过浙江省社会主义教育第六分团策划组织杭州","box":[[189,394],[1064,394],[1064,418],[189,418]]},{"text":"市郊农民进入浙江大学校园，反击“右派”学生，开启了挑动农民","box":[[188,442],[1066,442],[1066,469],[188,469]]},{"text":"进城，挑动群众斗学生的先例。（见《省联总大事记》）","box":[[186,492],[953,490],[953,517],[186,519]]},{"text":"安吉县委派工作组和联络员，提出“把火力引向牛鬼蛇神”、","box":[[246,540],[1048,538],[1048,565],[246,567]]},{"text":"“内外有别”、“大字报不要上街”。（见《安吉党史》)","box":[[203,587],[984,586],[984,617],[203,618]]},{"text":"勤县县委召开全县党员干部会议，传达中共中央和省委有关文","box":[[247,638],[1069,635],[1069,662],[247,665]]},{"text":"化大革命的6个文件，声讨“阶级敌人”的反党罪行。勤县县委办","box":[[188,687],[1067,683],[1067,710],[188,714]]},{"text":"公室印发县委常委扩大会议《对当前工作的问题的意见》，指出，","box":[[187,734],[1053,732],[1053,762],[187,764]]},{"text":"农村文化大革命，横扫一切牛鬼蛇神和“破四旧。”（见《鄞县县","box":[[186,782],[1070,780],[1070,811],[186,813]]},{"text":"志》）","box":[[187,833],[263,833],[263,862],[187,862]]},{"text":"桐庐县委召开干部大会，部署文化大革命运动。作出揭发坏","box":[[249,883],[1069,879],[1069,906],[249,909]]},{"text":"人、管制“四类分子”、整顿俱乐部，抓“破四旧”典型等6条规","box":[[186,929],[1073,926],[1073,957],[186,960]]},{"text":"定。（见《桐庐党史》）","box":[[187,980],[509,978],[509,1006],[187,1008]]},{"text":"省委为了控制省级机关的文化大革命，采取了组织措施，着手","box":[[248,1029],[1070,1027],[1070,1054],[248,1056]]},{"text":"将那些有危险的“知情人”调离杭州。李丰平指示公安厅长吕剑","box":[[187,1078],[1070,1077],[1070,1104],[187,1105]]},{"text":"光：“公安厅搞运动要掌握一条，凡是触及要害的人员必须立即调","box":[[186,1129],[1073,1126],[1073,1153],[186,1155]]},{"text":"离。”吕剑光将积极参加文化大革命的2百多名公安干部打成“反","box":[[188,1177],[1071,1177],[1071,1204],[188,1204]]},{"text":"革命”、“危险分子”，调到基层，下放到边远地区。（见《省联","box":[[183,1222],[1075,1224],[1075,1257],[183,1255]]},{"text":"总大事记》）","box":[[185,1273],[350,1277],[349,1305],[185,1301]]},{"text":"浙江某省医院护士×××（曾担任过江青的护士，因其怀孕，","box":[[246,1323],[1054,1325],[1054,1355],[246,1353]]},{"text":"江青通过王芳将其落实到省某医院担任护士）和她在省外事办公室","box":[[182,1373],[1074,1372],[1074,1401],[182,1402]]},{"text":"工作的丈夫（在中央办公厅警卫局工作过）被认为是危险人物，由","box":[[181,1421],[1073,1421],[1073,1454],[181,1454]]},{"text":"省政府副秘书长直接通知，紧急将他们一起调往丽水。不顾×××","box":[[181,1471],[1069,1470],[1069,1501],[181,1502]]},{"text":"即将分娩，其丈夫正在住院治疗，命令次日必须离开杭州。","box":[[184,1523],[979,1522],[979,1549],[184,1550]]},{"text":"7月13日江华等人迅速将刘少奇、邓小平以中央名义签发的","box":[[242,1573],[1071,1571],[1071,1598],[242,1600]]},{"text":"—25","box":[[923,1646],[1020,1646],[1020,1674],[923,1674]]},{"text":"一","box":[[1018,1647],[1044,1647],[1044,1670],[1018,1670]]}],"dimensions":{"height":1753,"width":1240}}