{"ocr_results":[{"text":"第二阶段群众性批判资产阶级反动路线","box":[[492,149],[1050,147],[1050,175],[492,177]]},{"text":"开始上街“破四旧”。","box":[[169,247],[462,250],[462,281],[169,278]]},{"text":"杭州市红卫兵(以市属一些中学的学生为主)纷纷走上街头刷标","box":[[230,296],[1052,297],[1052,327],[230,326]]},{"text":"语、贴大字报，“大破四旧”，从一些商店的招牌、街道路标着","box":[[168,346],[1050,345],[1050,374],[168,376]]},{"text":"手，并将延龄路改为延安路，杭览路改为红卫兵路，都锦生丝织厂","box":[[170,395],[1051,393],[1051,420],[170,422]]},{"text":"改为东方红丝织厂，王星记扇厂改为东风扇厂，张小泉剪刀厂改为","box":[[170,441],[1050,443],[1050,470],[170,468]]},{"text":"杭州剪刀厂等等。（见《浙江文革纪事》）","box":[[168,490],[741,492],[741,519],[168,517]]},{"text":"宁波市农业职业中学的红卫兵(中学生)敲锣打鼓涌上街头，向","box":[[232,540],[1051,540],[1051,567],[232,567]]},{"text":"东福园菜馆、绿宝照相馆等单位提出“倡议”，要求立即改换剥削","box":[[170,588],[1051,588],[1051,615],[170,615]]},{"text":"阶级遗留下来的臭招牌。","box":[[170,635],[494,635],[494,662],[170,662]]},{"text":"紧接着，全省地、县的许多学校红卫兵（老），走向社会，以","box":[[232,684],[1051,684],[1051,711],[232,711]]},{"text":"“破四旧”为名，对地富反坏分子和其他群众实行打、砸、抄，一","box":[[188,731],[1049,732],[1049,759],[188,758]]},{"text":"些没有改造好的地、富、反、坏、右分子和流氓阿飞被揭露和游","box":[[167,778],[1052,779],[1052,809],[167,808]]},{"text":"斗。如据杭州市统计，抄家13518户，抄没黄金53万余克，白银","box":[[169,827],[1052,828],[1052,856],[169,855]]},{"text":"1000余公斤，银元115000枚，宝石30000粒，玉器6500件，人民","box":[[168,875],[1053,878],[1053,904],[168,902]]},{"text":"币、国债券270万元等。（见《杭州党史》）","box":[[170,925],[758,925],[758,952],[170,952]]},{"text":"据安吉统计，全县各公社，前一阶段运动中，被抄家3775户，","box":[[230,974],[1036,975],[1036,1002],[230,1001]]},{"text":"被戴帽游街总人数643人，被捆、打、斗363人，其中五类分子占绝","box":[[167,1021],[1052,1023],[1052,1051],[167,1049]]},{"text":"大部分。（见《安吉党史》）","box":[[166,1071],[552,1071],[552,1098],[166,1098]]},{"text":"全省被走资派和工作组定为“反革命”、“右派”、“牛鬼蛇","box":[[228,1119],[1056,1119],[1056,1152],[228,1152]]},{"text":"神”的教师，被红卫兵押着走在队伍里，接受所谓“破四旧”的教","box":[[165,1166],[1056,1168],[1056,1198],[165,1196]]},{"text":"育。如仙居各中学红卫兵在县委工作组带领下，甚至将所谓“黑","box":[[165,1215],[1054,1217],[1054,1247],[165,1245]]},{"text":"帮”、“右派”、“反革命”的教师五花大绑地押着到社会上“破","box":[[163,1262],[1057,1265],[1057,1298],[163,1295]]},{"text":"四旧”和抄地富反坏右家的金银珠宝。（《仙居文革大事记》。）","box":[[167,1314],[1041,1316],[1041,1344],[167,1342]]},{"text":"资产阶级反动路线仍笼罩着浙江大地，革命造反派仍被压在资","box":[[229,1361],[1053,1363],[1053,1392],[229,1390]]},{"text":"产阶级反动路线的五雷山下。","box":[[165,1410],[551,1413],[550,1440],[165,1437]]},{"text":"同日，浙江美术学院成立了“红卫兵战斗队”(新)，主要头头","box":[[229,1459],[1053,1460],[1053,1488],[229,1487]]},{"text":"张永生(学生)、杜英信(教师)。（见《浙江文革纪事》)","box":[[166,1505],[920,1507],[920,1537],[166,1535]]},{"text":"8月25日杭州大学、浙江美术学院、浙江大学、杭州外语专","box":[[227,1555],[1053,1557],[1053,1587],[227,1585]]},{"text":"—33—","box":[[901,1632],[1032,1629],[1033,1660],[902,1663]]}],"dimensions":{"height":1753,"width":1240}}