{"ocr_results":[{"text":"文革期间中央领导接见浙江代表的记录稿","box":[[501,152],[1046,153],[1046,180],[501,179]]},{"text":"富经验。浙江的问题，怎么办，要大家考虑一下，怎样解决有利，","box":[[186,255],[1030,254],[1030,284],[186,285]]},{"text":"多想几种可能性，多想几种办法。浙江不搞好，主席很不安，我跟","box":[[187,304],[1047,304],[1047,331],[187,331]]},{"text":"龙潜说，浙江不搞好，主席怎么去，主席休息的地方总要搞好。","box":[[185,352],[1025,353],[1025,379],[185,378]]},{"text":"不要怕犯错误，有问题多思索一下，积累一些经验。政权机","box":[[243,400],[1045,400],[1045,427],[243,427]]},{"text":"构、党的机构，应该经过文化大革命考验的机关。机构精悍，不这","box":[[185,450],[1045,450],[1045,474],[185,474]]},{"text":"样庞大，密切联系群众的，真正按毛泽东思想办事的，现在“三结","box":[[184,499],[1045,499],[1045,523],[184,523]]},{"text":"合”机构的，除了部队、干部、群众组织外，还要老、中、小，这","box":[[182,545],[1046,545],[1046,575],[182,575]]},{"text":"样可以交班。现在看看省委书记都是一样年龄，要交班一起交班，","box":[[183,595],[1027,595],[1027,622],[183,622]]},{"text":"这样行吗？","box":[[181,641],[315,641],[315,669],[181,669]]},{"text":"宁波可以写一个通告，改组革委会。","box":[[242,690],[718,692],[718,719],[241,717]]},{"text":"（张永生说：张茂勋对我们说，要改正错误，发表通告，支持","box":[[243,740],[1041,740],[1041,767],[243,767]]},{"text":"省联总，反对红暴会，支持造反派，还要求省联总调查组，在宁波","box":[[184,788],[1043,787],[1043,814],[184,815]]},{"text":"留一段时间，可以不可以。）","box":[[186,837],[563,837],[563,864],[186,864]]},{"text":"张春桥同志说：他们要调查组留在那儿是可以的，杭州条件成","box":[[243,884],[1042,882],[1042,909],[243,911]]},{"text":"熟的话，可先成立杭州市革命委员会，稳定杭州局势。","box":[[184,932],[898,931],[898,958],[184,959]]},{"text":"（代表们说：杭州市领导干部还没有确定，杭州市跟省有密切","box":[[242,982],[1041,979],[1041,1006],[243,1009]]},{"text":"关系，省里是否也可以象四川一样，成立一个革命委员会筹备小","box":[[184,1031],[1042,1027],[1042,1054],[184,1058]]},{"text":"组。）张春桥同志说：这也是一种办法，你们先提一个名单看，金","box":[[183,1079],[1045,1075],[1045,1102],[183,1106]]},{"text":"华问题听说二十军60师开始在转了。但是金华军分区机关干部却拍","box":[[183,1128],[1044,1123],[1044,1150],[183,1154]]},{"text":"来一份电报，说不同意中央首长讲不要动员农民进城，讲了许多","box":[[183,1176],[1041,1172],[1041,1199],[183,1203]]},{"text":"“理由”，说农民进城好得很！","box":[[203,1224],[591,1223],[591,1251],[203,1252]]},{"text":"去年十一月，我就是在这里(指政协礼堂)接见师范学院1000多","box":[[240,1272],[1044,1269],[1044,1299],[241,1302]]},{"text":"名同学，他们要罢李学智的官，我说罢官是容易的，你们要做到不","box":[[184,1320],[1045,1320],[1045,1350],[184,1350]]},{"text":"罢官，把李学智斗倒斗垮。魏文伯、李丰平在中央开会还压我，说","box":[[184,1368],[1045,1367],[1045,1396],[184,1397]]},{"text":"我为什么不跟浙江省委商量一下，我说我个人意见为什么不能发","box":[[182,1415],[1043,1416],[1043,1446],[182,1445]]},{"text":"表，那些同学就是现在金二司的同学吗？（回答：是的。)金三司怎","box":[[181,1463],[1043,1464],[1043,1495],[181,1494]]},{"text":"么样？（回答：金三司是由原来赤子队变过来的保守组织。金华是","box":[[182,1512],[1044,1513],[1044,1544],[182,1543]]},{"text":"否可以成立一个部队支左委员会，664、703等单位派代表参加。)","box":[[181,1561],[1048,1561],[1048,1594],[181,1594]]},{"text":"—373—","box":[[877,1636],[1017,1636],[1017,1667],[877,1667]]}],"dimensions":{"height":1753,"width":1240}}