{"ocr_results":[{"text":"浙江省文化大革命大事记","box":[[229,153],[620,152],[620,179],[229,180]]},{"text":"二、窃取“红卫军”领导权的一小撮顽固坚持反动立场，为非","box":[[282,248],[1045,246],[1045,276],[282,278]]},{"text":"作岁的人，应依法处理；参加这个组织的群众，应欢迎他们脱离","box":[[227,297],[1044,294],[1044,321],[227,324]]},{"text":"“红卫军”组织，参加到革命造反派组织里来。","box":[[244,345],[826,344],[826,371],[244,372]]},{"text":"三、决不允许走资派对受蒙蔽参加过“红卫军”的基层组织头","box":[[283,392],[1046,387],[1046,415],[283,420]]},{"text":"头和广大战士进行打击报复。","box":[[227,440],[588,440],[588,467],[227,467]]},{"text":"1月25日省、市革命造反派战士3万余人，举行“浙江省暨","box":[[281,487],[1049,482],[1049,512],[281,517]]},{"text":"杭州市革命造反派彻底摧毁反革命经济主义斗争大会”。省委书","box":[[222,535],[1048,530],[1048,560],[223,565]]},{"text":"记处书记、副省长吴宪、杭州市市长王子达等人接受批判。大会","box":[[222,583],[1048,577],[1048,607],[223,613]]},{"text":"通过了《给毛主席的致敬电》。会后举行游行。（见《杭州党","box":[[223,632],[1049,626],[1049,653],[223,658]]},{"text":"史》）","box":[[224,677],[296,677],[296,706],[224,706]]},{"text":"同日，为了热烈欢呼毛主席关于“人民解放军应积极支持革命","box":[[281,726],[1049,721],[1049,750],[281,755]]},{"text":"左派”指示和中共中央、国务院、中央军委、中央文革小组发布","box":[[224,775],[1048,770],[1048,797],[224,802]]},{"text":"《关于人民解放军坚决支持革命左派群众的决定》，驻浙七三五○","box":[[238,822],[1048,818],[1048,846],[239,850]]},{"text":"和六四○九部队、海军部队分别在杭州市区和郊区举行游行。广大","box":[[224,869],[1049,864],[1049,894],[224,898]]},{"text":"指战员表示，最坚决地执行毛主席的命令，决心用鲜血和生命保卫","box":[[226,916],[1048,913],[1048,940],[226,943]]},{"text":"以毛主席为代表的无产阶级革命路线，坚决站在无产阶级革命派一","box":[[226,964],[1048,961],[1048,988],[226,991]]},{"text":"边，誓做革命左派群众的坚强后盾。（见《浙江日报》）","box":[[223,1011],[935,1008],[935,1037],[223,1040]]},{"text":"同日，龙潜、张秀龙等人借拥护中共中央决定之名，举行全副","box":[[280,1057],[1047,1055],[1047,1086],[280,1088]]},{"text":"武装游行，并专门调来骑兵显威。游行前，声言说：“要扬眉吐","box":[[224,1105],[1047,1104],[1047,1133],[224,1134]]},{"text":"气”，“我们要反击了”，“今天要出出气，给他(指造反派)颜色","box":[[223,1148],[1049,1145],[1049,1181],[223,1184]]},{"text":"看看”。游行队伍回到省军区门口时，与省、市革命造反派发生大","box":[[223,1199],[1048,1198],[1048,1228],[223,1229]]},{"text":"规模冲突，造成革命造反派群众许多人受伤。后来周总理来电严厉","box":[[223,1246],[1047,1245],[1047,1275],[223,1276]]},{"text":"批评了龙潜、张秀龙。（见《省联总大事记》）","box":[[223,1293],[815,1292],[815,1323],[223,1324]]},{"text":"同日，“省联总”《红色风暴》发表了《江华反党反社会主","box":[[277,1339],[1043,1337],[1043,1370],[277,1372]]},{"text":"义、反毛泽东思想罪行铁证如山》文章。","box":[[222,1387],[722,1385],[722,1416],[222,1418]]},{"text":"同日，《浙江日报》发表社论《大造经济主义的反，一反到","box":[[278,1434],[1042,1434],[1042,1464],[278,1464]]},{"text":"底》。","box":[[224,1483],[313,1483],[313,1511],[224,1511]]},{"text":"1月27日驻浙陆海空三军代表和省、市革命造反派4万多","box":[[277,1528],[1041,1531],[1041,1562],[277,1559]]},{"text":"—66—","box":[[243,1598],[357,1601],[356,1632],[242,1629]]}],"dimensions":{"height":1753,"width":1240}}