{"ocr_results":[{"text":"人受伤。事件后，“革联”撤至郊区杏林，直至1968年大联合才","box":[[259,298],[1783,297],[1783,355],[259,356]]},{"text":"返回学校，","box":[[261,394],[504,397],[503,448],[260,445]]},{"text":"（据有关资料整理）","box":[[1299,489],[1665,486],[1665,528],[1299,530]]},{"text":"厦大校内“八·二武斗事件”有关材料摘引","box":[[335,718],[1707,715],[1707,778],[336,781]]},{"text":"（摘要）","box":[[877,827],[1169,827],[1169,896],[877,896]]},{"text":"，“八·二武斗事件”爆发点，“革联”抓打张××。","box":[[368,1052],[1703,1038],[1703,1099],[369,1113]]},{"text":"1967年7月30下午，“厦大促联”女学生张××在校门口看","box":[[367,1144],[1783,1140],[1783,1190],[367,1194]]},{"text":"大字报，为大字报中所述的厦门纺织厂陈××的死亡原因与革联","box":[[262,1239],[1785,1233],[1785,1282],[262,1289]]},{"text":"学生争执，后被革联派学生绑架到大南八号楼（造反楼）地下","box":[[260,1332],[1784,1325],[1784,1376],[261,1382]]},{"text":"室。革联后又抓了促联人员数人关于地下室，并打了人。","box":[[260,1422],[1588,1420],[1588,1470],[261,1473]]},{"text":"二、促联示威逼迫革联放人，双方谈判破裂。","box":[[373,1517],[1424,1512],[1424,1566],[374,1571]]},{"text":"当晚，促联发动群众包围造反楼，同时抓了革联派的几个","box":[[372,1609],[1783,1604],[1783,1654],[372,1659]]},{"text":"人·并派出代表两人到造反楼谈判，但双方争执不下，几乎动","box":[[232,1702],[1791,1682],[1792,1752],[233,1772]]},{"text":"武，谈判破裂。","box":[[255,1797],[603,1791],[604,1845],[256,1851]]},{"text":"三、双方对崎，相互抄、砸对方的住地及成员家庭。","box":[[370,1887],[1591,1885],[1591,1938],[370,1940]]},{"text":"双方谈判不成，促联据守丰庭（一）楼与造反楼形成对崎，","box":[[371,1982],[1747,1974],[1747,2024],[371,2031]]},{"text":"双方群众以石头砖块互攻，并抄砸对方的住地和有关人员的家。","box":[[264,2076],[1756,2069],[1756,2116],[264,2123]]},{"text":"国、校外同派声授，予盾进一步激化。","box":[[373,2170],[1266,2166],[1266,2213],[374,2216]]},{"text":"8月1日，厦大革联派两个人到厦门市请求同派群众支援。","box":[[378,2264],[1755,2257],[1755,2305],[379,2312]]},{"text":"促联头头也开会研究对策，决定“武攻”。促派先从后山用石块","box":[[265,2357],[1785,2349],[1785,2398],[266,2407]]},{"text":"进攻保卫科大楼和厦大幼儿园，并抓走一些守卫的革派人员，厦","box":[[263,2451],[1788,2439],[1788,2490],[263,2501]]},{"text":"门市的促派组织也派人进入校内围攻造反楼。晚上造反楼里的人","box":[[259,2545],[1783,2534],[1783,2579],[259,2591]]},{"text":"员撤走了一部份。同时，外面两派也发生个别摩擦，","box":[[265,2636],[1488,2628],[1488,2678],[266,2685]]},{"text":"五，八·二武斗，死亡林金铭等三人","box":[[366,2727],[1258,2717],[1258,2774],[367,2785]]},{"text":":","box":[[1496,2761],[1576,2758],[1577,2789],[1497,2792]]},{"text":"-Sf","box":[[1225,2776],[1247,2776],[1247,2789],[1225,2789]]}],"dimensions":{"height":3063,"width":2084}}