{"ocr_results":[{"text":"了肯定，而吴大胜却左一个为什么，右一个为什么。吴大胜这样大叫大，到底是为什","box":[[159,173],[2221,162],[2221,242],[159,253]]},{"text":"别的，光说去年九月你去北京吊毛主席逝世，临上飞机前，你要华林森向“上海的同","box":[[2527,182],[4524,246],[4522,308],[2525,243]]},{"text":"么？说穿了，就是因为“四人帮”要把省委主要负责同志打成幕后策划者，吴大胜在常","box":[[157,259],[2217,248],[2217,320],[157,332]]},{"text":"志”反映所谓江苏问题。华林森与“四人帮”的关系，华林森和“四人帮”在上海余党","box":[[2525,270],[4522,326],[4520,384],[2523,327]]},{"text":"委会上作这样一番表现，无非是为了“立此存照”，有朝一日，好向“四人帮”邀功请","box":[[157,339],[2219,328],[2219,402],[157,414]]},{"text":"的关系，你是很清楚的。吴大胜你讲的“上海同志”是什么同志，为什么江苏的问题要","box":[[2525,353],[4522,405],[4520,462],[2523,411]]},{"text":"赏！那么，怎样把“幕后策划者”揪出来呢？吴大胜讲到这里，更加趾高气扬，得意忘","box":[[155,419],[2219,411],[2219,486],[155,494]]},{"text":"向“上海的同志”反映，你不是和他们有深仇大恨吗？为什么要向和你有深仇大恨的上","box":[[2523,437],[4520,483],[4519,539],[2521,493]]},{"text":"形，他说“要联系实际批邓，必须联系江苏的实际”。中央的四号、五号文件和华主席","box":[[155,497],[2219,492],[2219,568],[155,574]]},{"text":"海同志告黑状乞怜讨好去抱他们的大腿呢？毛主席刚逝世，有问题不向华主席为首的党","box":[[2521,521],[4520,563],[4519,617],[2520,575]]},{"text":"的历次讲话中，从来没有讲过批邓要联系地方的实际。吴大胜接过“四人帮”批邓另搞","box":[[155,581],[2217,573],[2217,648],[155,656]]},{"text":"中央反映，你反要华林森去向“四人帮”告状，这是什么性质的问题，不是昭然若揭","box":[[2521,607],[4516,645],[4515,695],[2520,657]]},{"text":"一套的阴谋，借联系实际为名，配合“四人帮”妄图搞跨省委，搞乱江苏。你的讲话记","box":[[155,663],[2224,655],[2225,730],[155,737]]},{"text":"吗？不仅如此，当马天水在灵堂外边休息的时候，他也不放过机会，挤上去向马天水反","box":[[2519,681],[4516,721],[4515,777],[2518,737]]},{"text":"录俱在，现在你想抵赖，是赖不掉的。","box":[[166,762],[1056,762],[1056,806],[166,806]]},{"text":"映所谓江苏的问题，得钻就钻，得靠就靠，千方百计想通过“四人帮”的余党向“四人","box":[[2522,767],[4512,803],[4511,853],[2522,817]]},{"text":"吴大胜在所谓揭发检查中，口口声声说：他和帮派小集团人物频繁接触，都是向他","box":[[264,825],[2215,823],[2215,892],[264,894]]},{"text":"帮”表白效忠。吴大胜，告诉你，马天水已经交待了，徐景贤也交待了，你交待不交待","box":[[2523,845],[4516,883],[4515,935],[2522,897]]},{"text":"们“正面做工作”，“要他们认真学习，掌握斗争大方向”，要他们“在党委领导下，","box":[[151,909],[2195,905],[2195,972],[151,976]]},{"text":"随你的便，但人证俱在，你想吴大赖是赖不掉的。毛主席逝世以后，“四人帮”加快了","box":[[2524,927],[4512,961],[4511,1011],[2523,977]]},{"text":"抓革命、促生产”。果真如此，岂不很好。不但不应该要吴大胜检查问题，而是应该替","box":[[151,991],[2215,987],[2215,1054],[151,1058]]},{"text":"篡党夺权的步伐，吴大胜也认为解决所谓江苏问题时机到了，命往杨广立、华林森身","box":[[2522,1007],[4512,1041],[4511,1091],[2522,1057]]},{"text":"吴大胜评功摆好，才是道理。可惜，吴大胜嘴里的吴大胜，同实际生活中的吴大胜，硬","box":[[155,1073],[2215,1074],[2215,1138],[155,1136]]},{"text":"上靠，命往“四人帮”身上靠，难道天下真有这样反“四人帮”的英雄吗？","box":[[2522,1087],[4283,1118],[4283,1168],[2522,1137]]},{"text":"是对不上号。岂但对不上号，而是恰恰相反。有事实为证：你说你向山头人物专“做正","box":[[151,1153],[2214,1156],[2213,1220],[151,1216]]},{"text":"现在，揭发、批判、清查“四人帮”的斗争已经象燎原烈火燃遍全省，燃遍全国。","box":[[2626,1169],[4486,1198],[4486,1248],[2625,1219]]},{"text":"面工作”，那你为什么积极支持孔庆荣，以莫须有的罪名，硬要把汪冰石同志打成现行","box":[[155,1238],[2214,1238],[2214,1300],[155,1300]]},{"text":"奉劝吴大胜不要再迷信唯心主义、形而上学，又一次错误地估计形势，不要把自已置于","box":[[2520,1247],[4514,1274],[4513,1330],[2520,1303]]},{"text":"反革命？你说你要帮派小集团人物“掌握斗争大方向”，那你为什么对苏州的张勇等人","box":[[155,1320],[2212,1320],[2212,1382],[155,1382]]},{"text":"同广大干部群众对立的地位。在这场斗争中，我们始终坚持摆事实，讲道理，区别对待，坚","box":[[2520,1329],[4512,1356],[4512,1408],[2520,1381]]},{"text":"围攻地委领导同志，一再默不作声，公安部门要采取措施，你却百般阻拦？你说你要帮","box":[[157,1408],[2208,1406],[2208,1458],[157,1460]]},{"text":"决执行党的政策。只要你肯老老实实，向党交代，彻底揭发，我们还是欢迎的。当然，","box":[[2517,1408],[4518,1432],[4517,1488],[2516,1463]]},{"text":"派小集团人物“在党委领导下，抓革命、促生产”，那你为什么对华林森派大批的人来","box":[[153,1486],[2210,1484],[2210,1540],[153,1542]]},{"text":"要是有人企图利用党的政策的宽大，玩弄花招，制造谣言，施放暗箭，挑拨离间，做小动","box":[[2520,1491],[4512,1516],[4512,1566],[2520,1542]]},{"text":"到南京围攻省委，不讲半句话？当常委会上提出“水佐岗事件”要向中央写报告，你又","box":[[155,1570],[2204,1566],[2204,1620],[155,1624]]},{"text":"作，搞所谓“合法斗争”，那就是自绝于党、自绝于人民。至于我们，决心是下定了","box":[[2519,1573],[4510,1596],[4510,1646],[2518,1624]]},{"text":"为什么和杨广立一唱一和，命反对？大量事实证明，“屠宋”、“登攀”之流接二","box":[[153,1650],[2206,1646],[2206,1702],[153,1706]]},{"text":"的，坚决按照华主席、党中央的路线、方针、政策办事，坚持斗争大方向，“四人帮”","box":[[2519,1653],[4488,1674],[4488,1724],[2518,1704]]},{"text":"连三地去找你，并不是为了接受你的所谓“正面教育”；你对他们热情接待，确是为了","box":[[153,1735],[2201,1732],[2201,1782],[153,1786]]},{"text":"插手江苏、搞乱江苏的问题，一定要查清，不获全胜，决不收兵！","box":[[2520,1735],[4012,1750],[4011,1801],[2520,1786]]},{"text":"要他们掌握什么“大方向”。不过，这个大方向，是“四人帮”和你们的斗争大方向，","box":[[155,1816],[2175,1808],[2175,1860],[155,1868]]},{"text":"一九七七年一月三十一日","box":[[3831,1828],[4400,1832],[4399,1883],[3831,1879]]},{"text":"指向以毛主席、华主席为首的党中央的大方向，而不是我们党的斗争大方向而已。你和","box":[[155,1898],[2208,1888],[2208,1944],[155,1953]]},{"text":"[转自中共江苏省委三届九次全委（扩大）会议揭发批判发言材料之四]","box":[[2760,1901],[4381,1912],[4381,1963],[2760,1951]]},{"text":"他们勾得那么紧，都是出于一种政治斗争的需要。说穿了，无非是为了上下串通，里应","box":[[153,1981],[2208,1972],[2208,2022],[153,2032]]},{"text":"外合，搞垮省委，搞乱江苏，为“四人帮”及其在江苏的代理人“三搞一篡”效劳。与","box":[[149,2061],[2208,2050],[2208,2106],[150,2117]]},{"text":"你勾结的那些帮派小集团人物都还在，你的一些谈话记录也还在，现在想把你们的那些","box":[[151,2143],[2208,2130],[2208,2188],[152,2201]]},{"text":"见不得人的勾当，一笔勾销，办得到吗？","box":[[151,2227],[1108,2221],[1108,2272],[152,2277]]},{"text":"吴大胜在所谓揭发检查的结尾，还使出了一个绝招，就是所谓他同“四人帮”是有","box":[[258,2303],[2204,2296],[2204,2354],[259,2361]]},{"text":"“深仇大恨”的。这里，吴大胜竟把自已打扮成是一个受“四人帮”迫害、坚决反“四人","box":[[151,2382],[2210,2372],[2210,2441],[152,2451]]},{"text":"帮”的英雄了。我们真是有眼不识泰山，失敬得很！吴大胜你既然同“四人帮”有深仇","box":[[148,2465],[2206,2456],[2206,2519],[148,2529]]},{"text":"大恨，究竟仇在何处，恨在那里呢？不错，你说“四人帮”极为凶残地要将大批干部","box":[[144,2544],[2206,2542],[2206,2605],[144,2607]]},{"text":"打成走资派，置于死地。那么，这些“四人帮”要置于死地的走资派中，有你吴大胜","box":[[148,2626],[2204,2626],[2204,2689],[148,2689]]},{"text":"吗？你说“四人帮”一时说这个是特务，一时说那个要谋害他们，制造骇人听闻的假","box":[[148,2707],[2204,2707],[2204,2771],[148,2771]]},{"text":"象，对革命同志竭尽摧残追害，实行法西斯专政，那么这些受“四人帮”摧残追害的","box":[[148,2789],[2204,2789],[2204,2853],[148,2853]]},{"text":"专政对象中有你吴大胜吗？你说“四人帮”穷凶极恶地把专政的矛头指向党内，那么","box":[[144,2866],[2206,2868],[2206,2937],[144,2935]]},{"text":"“四人帮”把矛头指到了你吴大胜身上吗？江苏人民不会忘记，你也不应该这样健忘，","box":[[166,2946],[2177,2951],[2176,3018],[166,3013]]},{"text":"和“四人帮”亦步亦趋，处心积虑，想把江苏大批革命干部、革命群众打成反革命，而","box":[[142,3031],[2201,3031],[2201,3100],[142,3100]]},{"text":"且实际上已经打成过反革命，这样的人是有的，到底是谁，你吴大胜心里明白。我们认","box":[[140,3113],[2204,3113],[2204,3182],[140,3182]]},{"text":"（共印2600份）","box":[[4098,3145],[4442,3145],[4442,3197],[4098,3197]]},{"text":"本期发至基层党支部、革委会","box":[[3319,3164],[3979,3143],[3981,3204],[3321,3226]]},{"text":"内部刊物","box":[[2567,3176],[2786,3183],[2785,3242],[2566,3236]]},{"text":"注意保存","box":[[2893,3181],[3110,3176],[3111,3236],[2894,3240]]},{"text":"为你还是不要装成受“四人帮”追害的英雄为好。假的就是假的，伪装应当剥去。不说","box":[[137,3192],[2204,3192],[2204,3266],[137,3266]]},{"text":"19","box":[[4338,3281],[4405,3281],[4405,3339],[4338,3339]]},{"text":"18","box":[[246,3316],[314,3316],[314,3374],[246,3374]]}],"dimensions":{"height":3456,"width":4608}}