{"ocr_results":[{"text":"来，孙稼轩果然去找了王楚滨、雷绍典无理纠缠，并向《人民日报》两名“记者”告了","box":[[179,148],[2190,108],[2192,188],[180,228]]},{"text":"结，而是大搞分裂活动；在手法上，不是光明正大，而是大搞阴谋诡计。他根本不是正","box":[[2536,154],[4487,196],[4485,259],[2534,217]]},{"text":"省、市委的黑状。吴大胜为什么要庇护孙雨笑？很明显，孙雨笑是吴大胜一手扶植的","box":[[175,226],[2194,188],[2196,268],[176,306]]},{"text":"确路线的代表，也不是受“四人帮”迫害的受害者，而是紧跟“四人帮”，配合杨广","box":[[2534,234],[4487,274],[4485,336],[2533,296]]},{"text":"“屠宋”这个帮派小集团里的人，孙曾经为吴大胜翻“三破坏”的案，发过声明，造过","box":[[197,311],[2192,273],[2194,342],[198,380]]},{"text":"立、华林森等人，在搞乱江苏、篡党夺权的阴谋活动中干了大量坏事的人。吴大胜的这","box":[[2535,314],[4487,352],[4485,408],[2534,370]]},{"text":"奥论，吹捧吴大胜在批邓中是“紧跟党中央干革命，立了新功的”。所以，吴大胜庇护","box":[[177,395],[2189,357],[2190,419],[178,457]]},{"text":"些问题，是有历史根源的。早在批林批孔运动之前，他就积极推行林彪反革命修正主义","box":[[2536,391],[4485,430],[4484,488],[2534,448]]},{"text":"孙雨笑也就不遗余力了。","box":[[179,473],[727,473],[727,529],[179,529]]},{"text":"路线，在深挖“五·一六”运动中犯了扩大化的严重错误，把成千上万的革命干部、革","box":[[2532,465],[4490,503],[4489,566],[2531,528]]},{"text":"（二）为现行反革命分子叶振根翻案。","box":[[293,553],[1153,544],[1154,599],[294,609]]},{"text":"命群众打成反革命；在批林批孔运动中，他又对抗中央指示，用破坏革命来破坏生产，","box":[[2532,545],[4455,583],[4454,639],[2531,601]]},{"text":"破坏批林批孔，犯下了“三破坏”的严重错误，受到了以毛主席为首党中央的严厉批","box":[[2530,618],[4494,658],[4493,719],[2529,679]]},{"text":"叶振根，原系南京三五二一厂工人，“伍灿哲”帮派小集团里的骨干，思想反动，","box":[[277,632],[2156,601],[2157,663],[278,693]]},{"text":"评。但是，吴大胜对于他自已的这些问题，从来没有做过认真的检查，相反，长期对党","box":[[2528,690],[4496,732],[4494,801],[2527,759]]},{"text":"多次恶毒攻击伟大领袖毛主席和敬爱的周总理，奸污妇女多人，去年八月三日依法拘","box":[[168,710],[2195,683],[2195,745],[169,771]]},{"text":"耿耿于怀。一次，省公安局向他催批一个文件，他讲：“我又不是第一书记！”还散","box":[[2526,769],[4498,809],[4496,876],[2525,836]]},{"text":"留。八月中旬，“伍灿哲”头目郝家驹和骨干徐起、于力去找吴大胜，讲了叶振根被","box":[[168,790],[2195,765],[2195,827],[168,851]]},{"text":"布什么：“省委内部有主要常委、次要常委！”批邓、反击右倾翻案风斗争开始后，他错","box":[[2528,843],[4496,885],[4494,952],[2527,910]]},{"text":"抓的事，吴大胜说：“我已经对公安局讲过了，在批邓中，群众贴大字报，要保护，不","box":[[166,868],[2195,847],[2195,908],[167,929]]},{"text":"误地估计了形势，私心、野心一起发作，积极投靠“四人帮”及其在上海的余党，积极","box":[[2532,925],[4499,965],[4498,1028],[2531,988]]},{"text":"允许借口群众过去有缺点、错误就抓人。你们写个材料，我来批一下，叫市里查一查”。","box":[[166,946],[2173,929],[2173,990],[166,1008]]},{"text":"向杨广立等人靠拢，参与“三搞一篡”的罪恶活动，妄图再一次把一大批革命干部打成","box":[[2532,1001],[4499,1043],[4498,1106],[2531,1065]]},{"text":"后来，郝家驹等三人写了一封为叶振根翻案的信，送给了吴大胜。吴大胜于八月廿一日","box":[[162,1026],[2189,1011],[2190,1072],[163,1088]]},{"text":"“走资派”“代理人”“幕后策划人”，并千方百计为他的“三破坏”问题翻案。吴大","box":[[2552,1078],[4501,1118],[4500,1187],[2551,1147]]},{"text":"在这封信上批：“请南京市委查处，结果告知”。","box":[[161,1106],[1403,1100],[1403,1158],[161,1164]]},{"text":"胜满以为看准了风向，找准了靠山，因此，他象押宝一样，把赌注全部押在“四人帮”","box":[[2524,1162],[4483,1196],[4482,1257],[2523,1223]]},{"text":"（三）为刑事犯罪分子张晓阳翻案。","box":[[283,1186],[1108,1188],[1108,1238],[282,1236]]},{"text":"身上，与杨广立等人抱得很紧，结果，老账未清，又犯新罪。但是，以英明领袖华主席","box":[[2530,1238],[4503,1276],[4502,1339],[2529,1301]]},{"text":"张晓阳，原系徐州铁路分局电务段工人，自一九七四年以来，纠集一伙犯罪分子，","box":[[266,1266],[2162,1253],[2162,1309],[266,1322]]},{"text":"为首的党中央，一举粉碎了“四人帮”，吴大胜的黄梁美梦也成了泡影。我们严正警告","box":[[2532,1322],[4503,1354],[4502,1412],[2531,1380]]},{"text":"大搞打、砸、抢犯罪活动，先后在徐州、南京、杭州等地抢劫机关、部队、厂矿吉普车","box":[[157,1346],[2200,1333],[2201,1391],[157,1404]]},{"text":"吴大胜，华主席在第二次全国农业学大寨会议上，已经把这场斗争的性质、方针、政策","box":[[2533,1402],[4503,1430],[4502,1488],[2533,1460]]},{"text":"六辆、卡车一辆，扰乱社会治安，破坏革命秩序，于一九七五年五月依法逮捕。去年八","box":[[155,1430],[2200,1417],[2201,1469],[155,1482]]},{"text":"再一次讲得很清楚了。华主席明确指出：我们同“四人帮”的矛盾是敌我矛盾。对于这","box":[[2532,1482],[4503,1512],[4502,1568],[2531,1538]]},{"text":"月三日孔庆荣去找吴大胜，谈到张晓阳问题，吴说：“要释放”。去年八月六日他们就","box":[[155,1508],[2204,1491],[2204,1549],[155,1566]]},{"text":"一点，你吴大胜必须有清醒的认识。华主席还指出，对跟着“四人帮”犯了错误的人，","box":[[2532,1560],[4470,1589],[4469,1646],[2531,1618]]},{"text":"炮制了一份为张晓阳翻案的所谓“人民来信”送给了吴大胜，八月十日吴就批了：“请","box":[[149,1592],[2204,1571],[2204,1627],[150,1648]]},{"text":"“只要把参与阴谋的那一套向党向人民讲清楚，同“四人帮”划清界限，我们就欢迎”。","box":[[2550,1633],[4498,1667],[4496,1730],[2549,1696]]},{"text":"公安局、法院联合调查，结果报省”。八月十七日，“登攀”的骨干陈克兴写信给徐州","box":[[153,1670],[2198,1653],[2199,1711],[154,1728]]},{"text":"如果企图利用党的政策的宽大，玩弄花招，搞什么“合法斗争”，蒙混过关，那是绝对","box":[[2532,1720],[4507,1747],[4506,1803],[2531,1776]]},{"text":"地区帮派小集团里的两个人说：一“关于张晓阳同志的事情，我也亲自去找了吴政委，问","box":[[149,1754],[2198,1732],[2199,1786],[150,1808]]},{"text":"办不到的。对于你的问题，我们是一定要搞清楚的。我们希望你赶快醒悟过来，彻底转","box":[[2532,1802],[4509,1825],[4508,1881],[2531,1858]]},{"text":"题是一定要解决的，这是毫无问题的。但为了尽快的解决问题，希望你们能把群众发动","box":[[153,1832],[2202,1810],[2203,1868],[154,1890]]},{"text":"变立场，揭发“四人帮”的滔天罪行，及其插手江苏的罪恶活动，老老实实地交代自己","box":[[2532,1880],[4509,1903],[4508,1961],[2531,1938]]},{"text":"起来，和市委汪冰石展开面对面的斗争。”吴大胜千方百计要为张晓阳翻案，就是想把","box":[[151,1916],[2202,1892],[2203,1948],[152,1972]]},{"text":"的问题，回到毛主席的革命路线上来。如果执迷不悟，继续顽抗，我们就坚决同你斗争","box":[[2533,1964],[4507,1983],[4506,2039],[2533,2020]]},{"text":"张晓阳放出来，利用他在铁路上的帮派小集团，把徐州搞乱，把铁路搞乱。","box":[[153,2000],[1908,1977],[1909,2028],[154,2050]]},{"text":"到底，不获全胜，决不收兵！","box":[[2535,2044],[3196,2054],[3195,2106],[2535,2096]]},{"text":"（四）为散布反动言论的王卫东开脱。","box":[[273,2078],[1152,2070],[1152,2121],[274,2128]]},{"text":"一九七七年一月三十一日","box":[[3333,2136],[3886,2142],[3886,2192],[3332,2186]]},{"text":"去年四月七日，团省委在连云港市召开区、局团委书记会议，团省委组织部长王卫","box":[[262,2160],[2202,2134],[2203,2186],[263,2212]]},{"text":"[转自中共江苏省委三届九次全委（扩大）会议揭发批判发言材料之五]","box":[[2771,2212],[4383,2222],[4383,2277],[2771,2268]]},{"text":"东在会上说：“大家眼晴要住中央，中央会不会出修正主义，政治局里那些人会出修","box":[[149,2240],[2202,2214],[2203,2270],[150,2296]]},{"text":"正主义，要排排队。”公然把矛头指向以毛主席为首的党中央。七月九日，机关追查组","box":[[149,2322],[2202,2298],[2203,2353],[150,2378]]},{"text":"向吴大胜汇报了这一情况，把连云港市揭发的材料也给吴看了，提出要加以追查。吴大","box":[[148,2406],[2200,2383],[2201,2435],[148,2458]]},{"text":"胜说：“这事我晓得，不查了。”第二天早晨，吴大胜拖了拖鞋到施兆祥家，通风报","box":[[146,2484],[2202,2461],[2203,2519],[146,2542]]},{"text":"信，说什么：“你们在连云港开会讲话有问题。”示意施兆祥注意。过了两天施兆祥派","box":[[146,2568],[2202,2547],[2203,2603],[146,2624]]},{"text":"团省委两个同志到机关追查组摸底，未得。吴大胜在追查中，对一些同志横加罪名，一","box":[[146,2648],[2197,2631],[2197,2689],[146,2706]]},{"text":"心要把一大批干部打成“反革命”，而对于王卫东这样严重的问题，又是通风报信，又","box":[[146,2728],[2199,2717],[2199,2773],[146,2784]]},{"text":"是百般开脱，不予追查，其原因，就是因为王卫东是他扶植和支持的帮派小集团里的","box":[[146,2810],[2202,2800],[2203,2856],[146,2866]]},{"text":"人，是他们一伙妄图搞乱江苏、篡权复辟的一个基干力量。","box":[[144,2896],[1569,2888],[1569,2938],[144,2946]]},{"text":"毛主席教导我们：“要搞马克思主义，不要搞修正主义；要团结，不要分裂；要光","box":[[253,2972],[2204,2966],[2204,3030],[253,3035]]},{"text":"明正大，不要搞阴谋诡计。”无可辩驳的大量事实证明，吴大胜违背“三要三不要”的","box":[[138,3054],[2204,3050],[2204,3111],[139,3115]]},{"text":"原则，在政治上，不是搞的马列主义，而是搞的修正主义；在组织上，不是维护党的团","box":[[135,3132],[2204,3128],[2204,3203],[135,3207]]},{"text":"15","box":[[4353,3220],[4423,3220],[4423,3277],[4353,3277]]},{"text":"14","box":[[236,3253],[306,3253],[306,3311],[236,3311]]}],"dimensions":{"height":3456,"width":4608}}