{"ocr_results":[{"text":"第十六章榆讨蘇聯發展模式奥第八次全國大會","box":[[402,68],[775,67],[775,85],[402,86]]},{"text":"業、連输業、農業、商業、财政等三十四个部门的匯報，毛主席那時工","box":[[116,152],[775,152],[775,169],[116,169]]},{"text":"作得很紧张，叫做床上地下」，就是起床就匯報，了匯報才上床休","box":[[116,188],[775,188],[775,205],[116,205]]},{"text":"息！這些報告根據周恩來的紀錄稿整理成文，而中央其他一些领導人也","box":[[115,222],[775,222],[775,242],[115,242]]},{"text":"經常参加匯報會，以總結建設的經驗。（十）","box":[[114,256],[531,258],[531,279],[114,277]]},{"text":"九五六年四月，毛澤東根據各匯報鲁及研究结果，在中央政治局","box":[[164,295],[775,295],[775,312],[164,312]]},{"text":"内作了<十大關係>（十一的報告，十大關傢包括：第一，發展重工業","box":[[115,328],[777,329],[777,349],[115,348]]},{"text":"和輕工業、農業的關係；第二，沿海和内地工業的關係；第三，經濟建","box":[[117,365],[775,365],[775,382],[117,382]]},{"text":"設和國防建設的關係；第四，國家、生產單位和生產者個人的關係；第","box":[[114,398],[776,399],[776,419],[114,418]]},{"text":"五，中央和地方的關係：第六，漢族和少數民族的關係；第七，黛和非","box":[[115,435],[775,435],[775,455],[115,455]]},{"text":"黛的係；第八，革命和反革命的關係；第九，是非關係；第十，中國","box":[[115,470],[774,471],[774,489],[115,488]]},{"text":"和外國的關係。報告開頭就指出：「特别值得注意的是，最近蘇聯方面暴","box":[[115,505],[776,506],[776,526],[115,525]]},{"text":"露了他們在建設社會王羲趟程中的一些缺點和錯，他們走過的鹭路，","box":[[116,543],[771,543],[771,560],[116,560]]},{"text":"你想走：了毛澤東强調應該批判地参辞其他國家在發展經驗中的长處，","box":[[117,578],[770,578],[770,595],[117,595]]},{"text":"不能盲目地學，切忌一切照抄，機械搬連。","box":[[116,612],[520,612],[520,631],[116,631]]},{"text":"毛澤東後来曾針對性地指出：","box":[[162,647],[433,647],[433,667],[162,667]]},{"text":"各部都有规章制度問題，搬蘇聯的很多，害人不。」建國之初，","box":[[160,699],[771,701],[771,721],[160,719]]},{"text":"没有瓣法，搬蘇聯的，這有一部分真理，但也不是全部真理。」不要硬","box":[[115,734],[775,736],[775,756],[115,754]]},{"text":"搬，硬搬就是不獨立思考，忘記了歷史上教條主義的教訓。」十二）","box":[[114,769],[752,770],[752,793],[114,792]]},{"text":"二中國共產的改革措施","box":[[114,838],[436,837],[436,861],[114,862]]},{"text":"在五六年九月的全國共產黛第八次全國代表大會及五七年二月毛澤","box":[[162,896],[775,896],[775,913],[162,913]]},{"text":"東發表的<關係正確處理人民内部矛盾的問题>的重要講話中，都將十","box":[[115,930],[775,930],[775,950],[115,950]]},{"text":"大關係的重要精神再作强調及引申，這些文件主要表蓬在解决經濟建","box":[[116,967],[774,967],[774,984],[116,984]]},{"text":"速度及策略、經濟管理體制改革及改善共產黛领導作用等三個主要方","box":[[114,1001],[774,1001],[774,1021],[114,1021]]},{"text":"面：","box":[[113,1035],[156,1035],[156,1057],[113,1057]]},{"text":"（1）經濟發展速度及投资策略","box":[[120,1090],[422,1090],[422,1110],[120,1110]]},{"text":"針對投資過多，發展速度脱離實際财力、物力的問题，周恩來及陳","box":[[159,1141],[774,1142],[774,1162],[159,1161]]},{"text":"217","box":[[736,1194],[767,1194],[767,1218],[736,1218]]}],"dimensions":{"height":1247,"width":864}}