{"ocr_results":[{"text":"第二十一章務宝路經濟的大救亡","box":[[474,64],[774,64],[774,81],[474,81]]},{"text":"度，只要生產隧的主權能落實，就不需再搞「责任田」。","box":[[114,148],[626,147],[626,167],[114,168]]},{"text":"但在此時，田家英改變了對「责任田」的看法，他為在手工動","box":[[158,183],[775,181],[775,201],[158,203]]},{"text":"的條件下，為克服經濟難關，个體家庭經濟有其优越性，而實際情况亦","box":[[114,219],[775,218],[775,238],[114,239]]},{"text":"證明包產到户對恢復生產有利，但當田家英将這个觀點向毛澤东匯報","box":[[114,255],[775,254],[775,274],[114,275]]},{"text":"時，毛澤東明確表態：","box":[[114,292],[324,292],[324,309],[114,309]]},{"text":"我們是要走群路線的，但有的時候，也不能完全群的，比如","box":[[163,343],[774,342],[774,362],[163,363]]},{"text":"搞包到户就不能。」（二十二)","box":[[113,378],[422,380],[422,400],[113,398]]},{"text":"一九六二年一月行的七千人大會普遍被為是中共全面推行務實","box":[[164,432],[775,430],[775,450],[164,452]]},{"text":"路線的起點，毛澤東在會上作出自我批，劉少奇明確提出「七分人","box":[[114,467],[772,465],[772,485],[114,487]]},{"text":"的觀點，然而，刺的是，包產到户在七千人大會上受到廣泛的批，","box":[[114,504],[770,501],[770,521],[114,524]]},{"text":"大力提倡责任田的安徽省委第一書記曾希里更因此而被免去職務。","box":[[114,537],[738,535],[738,558],[114,560]]},{"text":"三意識形態逆轉，毛澤東強調隋級门爭","box":[[114,589],[599,586],[599,610],[114,613]]},{"text":"一九六二年，國際形勢逆轉，分别是：","box":[[164,644],[518,642],[518,663],[164,664]]},{"text":"（1）中蘇關係進一步蕊化，一九六二年夏天，接連出現新疆居民集體逃","box":[[119,697],[775,696],[775,717],[119,718]]},{"text":"往蘇聯事件；","box":[[163,732],[289,732],[289,752],[163,752]]},{"text":"（2）印度藉中國在大羅後經濟元氣大傷的機會，越過「麥克馬洪線」，占","box":[[119,767],[775,767],[775,790],[119,790]]},{"text":"领中國领土，造成大规模境軍事衡突；","box":[[165,804],[550,804],[550,824],[165,824]]},{"text":"（3）美國加紧在越南南方的爭，牵制中國，使中國深受威叠。","box":[[119,839],[721,837],[721,858],[119,860]]},{"text":"在同一時期，台灣的國民黛政府亦藉中國經濟困難的處境，提出业","box":[[161,891],[776,889],[776,909],[161,911]]},{"text":"策劃反攻大睦」的行動，亚派遭特務潜入東南沿海地區，伺機行動。在","box":[[115,925],[776,924],[776,945],[115,946]]},{"text":"國内，由於經濟形勢仍困難，生活品短缺，公社和企業内的管理制度混","box":[[115,961],[775,961],[775,981],[115,981]]},{"text":"及不健全，韩部出現食污、欺群累的情况，亦加強了社會繁張的氣","box":[[116,996],[776,996],[776,1016],[116,1016]]},{"text":"氛。","box":[[113,1031],[157,1031],[157,1053],[113,1053]]},{"text":"在一九六二年八月，即離七千人大會七個月，中國的政治形勢明","box":[[160,1067],[776,1066],[776,1086],[160,1087]]},{"text":"產生變化。八月六日，在為備八届十中全會而於北戴河召開的工作","box":[[115,1102],[775,1101],[775,1122],[115,1123]]},{"text":"會上，毛澤東作了<隋級、形勢、矛盾>的講話，猛烈坪撃包產到户。","box":[[116,1137],[770,1135],[770,1158],[116,1160]]},{"text":"345","box":[[738,1192],[768,1192],[768,1213],[738,1213]]}],"dimensions":{"height":1247,"width":864}}