{"ocr_results":[{"text":"第二十三章文化大革命的成因及社會基","box":[[452,61],[774,62],[774,82],[452,81]]},{"text":"工，不許操作精密機床」，連動初期還有规定：！出身不好的工人有選","box":[[111,145],[773,147],[773,168],[111,166]]},{"text":"權但没有被選举權·..·表現是出身的结果呢，還是出身是表現的結果","box":[[110,180],[772,183],[772,203],[110,200]]},{"text":"呢？出身不好，便不能做行政、财會、保管等各種工作，也不能外","box":[[111,216],[772,219],[772,239],[111,236]]},{"text":"調。(主四十…)","box":[[110,251],[247,253],[247,274],[110,272]]},{"text":"不公平的封建等级制度為每個人深深打了烙印，而在這金字塔的上","box":[[154,298],[771,300],[771,321],[154,319]]},{"text":"層，牢牢地被共產黛員或各級乾部占據著，故當毛澤東號召群造反","box":[[108,334],[770,337],[770,357],[108,354]]},{"text":"時，很多以往由於出身不好而遭歧視的人熱烈地響應，翼常地积極投入","box":[[109,368],[770,372],[770,393],[109,389]]},{"text":"反特權隋級的造反行動。","box":[[111,405],[342,405],[342,426],[111,426]]},{"text":"（4）對長期思想、組織控制的反彈一一青少年的革命","box":[[111,453],[744,456],[744,480],[111,477]]},{"text":"心態","box":[[177,495],[232,495],[232,520],[177,520]]},{"text":"中共對青少年的政治教育十分重視，它著眼創造年青人的爱國心，","box":[[152,551],[765,554],[765,575],[152,572]]},{"text":"忠於领導與组織，持集體主義，增加對公事務的興趣及参舆，使他們","box":[[109,586],[769,590],[769,610],[109,606]]},{"text":"熱衷於政治運動，加強對法令规章的接受，使他們尊敬黛和政府的權威。","box":[[108,621],[766,625],[766,645],[108,641]]},{"text":"文革前，青年人透過共青圈被控制在共產万之下，做的服工","box":[[149,674],[769,677],[769,698],[149,695]]},{"text":"具。劉少奇之共產員的修養是入共青團必讀的文章、内容無非要求年","box":[[109,710],[769,713],[769,733],[109,730]]},{"text":"青人做万的服工具，這點在入团宣誓中也可以見到。我自己離開學校","box":[[108,746],[769,749],[769,769],[108,766]]},{"text":"後，亦是薰的召唤而去農村，而我所属的軍區直属農場，一切都團","box":[[108,781],[767,784],[767,805],[108,802]]},{"text":"組織的支配。」（四十二)","box":[[107,817],[330,820],[330,840],[107,837]]},{"text":"在文革前，年青人都缺乏個人自由意志：","box":[[150,869],[532,871],[532,891],[150,889]]},{"text":"「-個人小到大，不能自己决定自己的命運，包括教育，舆趣丶","box":[[148,918],[770,924],[770,948],[148,942]]},{"text":"話或汇默，以至職業、住宅、户口、口，一切都是被决定的。四十","box":[[106,956],[769,960],[769,983],[106,979]]},{"text":"三「中國的政制是對不容許民主、自由的，他們想為國家出力往往受","box":[[107,991],[769,996],[769,1019],[107,1014]]},{"text":"到限制，比喻即使想做倒粪工人，為人民服務，也必须由動局分配，","box":[[107,1028],[763,1032],[763,1052],[107,1048]]},{"text":"它不分配你，你甚至--辈子没工作。」","box":[[106,1059],[466,1065],[466,1092],[106,1086]]},{"text":"除了不能自己支配命運外，青少年亦面對很室息的社會環境：","box":[[149,1116],[728,1118],[728,1139],[149,1137]]},{"text":"407","box":[[728,1189],[759,1189],[759,1213],[728,1213]]}],"dimensions":{"height":1247,"width":864}}