{"ocr_results":[{"text":"建國以来（1949-1997","box":[[83,66],[269,66],[269,86],[83,86]]},{"text":"就改名為帝王将相部、才子佳人部，或者外國死人部。」","box":[[82,149],[615,151],[615,174],[82,172]]},{"text":"基於毛澤東的壓力，黛中央於一九六四年成立了由彭真、陵定-一、","box":[[126,197],[737,198],[737,218],[126,217]]},{"text":"康生、周揚、吴冷西组成的「中央文化革命五人小组」，統文化部及文","box":[[84,233],[744,233],[744,253],[84,253]]},{"text":"聯各協价的整風及批判作家的工作。","box":[[83,268],[424,268],[424,288],[83,288]]},{"text":"文界的批判蓮勤，影響到史学、哲学及經濟学等學術领域·報","box":[[128,306],[744,306],[744,323],[128,323]]},{"text":"先後點名批判了史學家翦伯赞的镶步政策」，周谷城的時代精神匯合","box":[[84,340],[744,340],[744,360],[84,360]]},{"text":"），哲學家杨獻真的合二為一」，經濟學家孫冶方的重視物質利益","box":[[84,376],[742,376],[742,393],[84,393]]},{"text":"原则和企業利润的經濟觀點。以上的學葡觀點皆是学葡界長期争和前","box":[[85,412],[742,412],[742,429],[85,429]]},{"text":"的老問题，但現在邻以政治批判方式解决，這就大大打擎了六零年","box":[[84,447],[742,447],[742,464],[84,464]]},{"text":"初開始较為活罐的學術讨氣氛。","box":[[84,481],[401,481],[401,501],[84,501]]},{"text":"毛澤東於一-九六五年針對海瑞能官一劇對陳伯蓬指出：海瑞能管的","box":[[129,518],[742,518],[742,535],[129,535]]},{"text":"要害問題是能官·嘉靖皇帝能了海瑞的官，一九五九年找們能了彭德懷","box":[[85,554],[742,554],[742,571],[85,571]]},{"text":"的官，彭德懷也是海瑞。","box":[[83,586],[325,588],[325,608],[83,606]]},{"text":"當毛澤東批判走資派」的總體策略是希望批判文藝作品入手，","box":[[129,624],[737,624],[737,641],[129,641]]},{"text":"而引出掌管此填政策的文化部以及北京市委的责任，再而将火頭上","box":[[85,659],[741,659],[741,676],[85,676]]},{"text":"燒，直接批判劉、等高層政。","box":[[82,692],[403,692],[403,712],[82,712]]},{"text":"然而，發表批判吴含文章的行動被北京市長彭真抵制著，作為北京","box":[[127,730],[742,730],[742,747],[127,747]]},{"text":"市長，真對姚文元不打招呼就批判他的副市長吴晗感到十分不满。基","box":[[83,763],[744,764],[744,784],[83,783]]},{"text":"於彭真的抵抗，毛澤東被迫於上海另立據點，事後毛曾指出文革：","box":[[82,799],[704,800],[704,820],[82,819]]},{"text":"「應一九六五年姚文元對海瑞官的批判開始，那個時候，我們這","box":[[123,846],[743,848],[743,868],[123,866]]},{"text":"個國家，在某一些部門··…被修正主義把持，真是水澄不進，針插不","box":[[83,883],[743,883],[743,903],[83,903]]},{"text":"進。当時我建曦彭真同志组織-下寫文章批判海瑞能官，但就在這個紅","box":[[83,919],[741,919],[741,939],[83,939]]},{"text":"色城市中，無能為力，只好到上海去组織。（注四）","box":[[83,953],[551,955],[551,976],[83,974]]},{"text":"姚文元寫的<斜歷史名劇海瑞能官），曾九易其稿，毛澤東親自修改","box":[[127,1003],[742,1003],[742,1020],[127,1020]]},{"text":"了三次，结果-一九六五年十\"一月於文匯報上刊登了，文章重點在於批","box":[[84,1036],[743,1037],[743,1057],[84,1056]]},{"text":"海瑞官-一劇是為右派分子翻案，借古今地批毛澤东政策·亚宣傅","box":[[82,1072],[743,1072],[743,1092],[82,1092]]},{"text":"隋級门爭調和。","box":[[82,1107],[250,1107],[250,1127],[82,1127]]},{"text":"姚文元的文章提出一個甚受爭的觀點，就是如何價歷史上的清","box":[[127,1144],[740,1144],[740,1161],[127,1161]]},{"text":"424","box":[[90,1196],[120,1196],[120,1217],[90,1217]]}],"dimensions":{"height":1247,"width":864}}