{"ocr_results":[{"text":"建國以（1949-1997）","box":[[94,68],[278,68],[278,85],[94,85]]},{"text":"在三月底當北京造反派以大字報攻擎葉劍英、陳毅及徐向前等軍","box":[[138,152],[755,152],[755,169],[138,169]]},{"text":"事袖時，多數軍區曾於同日垦行武装游行，進行示威表示抗，表達","box":[[95,187],[754,187],[754,204],[95,204]]},{"text":"了軍人對他們的老上司遭批门的重不滿。在（八條命令）後，衡擎軍事","box":[[97,223],[754,223],[754,240],[97,240]]},{"text":"機關的風很快便被煞住，軍隧大规模鎮壓造反派的情况在各地睦續發","box":[[94,257],[755,257],[755,277],[94,277]]},{"text":"生，其中事件包括有：","box":[[93,291],[304,291],[304,311],[93,311]]},{"text":"第-濟南軍區於二月下旬調動驻軍取缔以「山東省工人革命造反聊","box":[[136,327],[754,328],[754,348],[136,347]]},{"text":"合會總部為主體的十多個造反组織的成員，逮捕了大批造反群累，宣","box":[[95,363],[754,363],[754,383],[95,383]]},{"text":"布這些造反組織為反革命组，镇壓過後還連續數天出動大批满載全部","box":[[93,397],[755,398],[755,418],[93,417]]},{"text":"武装士兵的汽車示威游行。（注十八）","box":[[93,433],[418,434],[418,454],[93,453]]},{"text":"第二「得海二：二三事件中，青海軍區副司令趟永夫對「造反派]","box":[[137,469],[754,469],[754,489],[137,489]]},{"text":"進行鎖壓，在二月廿三日一天丙，「青海八一八红衢门隧和北京驻","box":[[93,504],[755,505],[755,525],[93,524]]},{"text":"青海紅衛兵多人被毅，二千多人受傷，數千人被逮捕禁，軍區宣布","box":[[94,541],[754,541],[754,561],[94,561]]},{"text":"|八一八紅衛门隧為反革命組，予以解散。（十九)以上一-切情况，","box":[[94,577],[750,577],[750,597],[94,597]]},{"text":"趙永夫皆向劍英作出電話報告，葉劍英亚指出：「你們打得對，打得","box":[[92,609],[753,612],[753,632],[92,629]]},{"text":"好！」（注二十）","box":[[92,645],[212,648],[212,668],[92,665]]},{"text":"第三武漢軍區把很多「造反组織]取缔，骨韩人物遭逮捕，--般成員","box":[[137,681],[754,681],[754,701],[137,701]]},{"text":"亦须登記及查。武漢於三月十七日深夜一時全市統一行動，逮捕造反","box":[[93,716],[754,717],[754,737],[93,736]]},{"text":"派群。三月二十一日，軍區又發表<通告>宣怖解散「造反]组「鋼工","box":[[93,752],[754,753],[754,773],[93,772]]},{"text":"總」及其所组織。在軍人的壓力下，很多尚未被取缔的组纷纷面瓦","box":[[93,787],[753,788],[753,808],[93,807]]},{"text":"解的危機，很多成員宣怖退出，在另一方面，對立面的「保守派]群累组","box":[[92,822],[754,823],[754,843],[92,842]]},{"text":"織得意洋洋：，在面對造反派批軍方镇壓行動為1三月黑風時，他們","box":[[95,860],[752,860],[752,877],[95,877]]},{"text":"则：三月東風浩激，軍管成續輝煌。」","box":[[95,896],[480,896],[480,913],[95,913]]},{"text":"在實力軍人對造反派探取强硬手段的情况下，毛澤東的造反行動遭","box":[[139,931],[753,931],[753,948],[139,948]]},{"text":"遇到文革進行以来最大的挫折。","box":[[94,967],[389,967],[389,984],[94,984]]},{"text":"第四節中央高層門爭與地方門爭的系","box":[[95,1039],[634,1040],[634,1064],[95,1063]]},{"text":"這節主要以四川的二月镇反事件，来反映高層门争舆地方门爭（軍","box":[[137,1106],[754,1106],[754,1126],[137,1126]]},{"text":"人舆造反派）間的微妙聯繁·","box":[[96,1142],[381,1142],[381,1162],[96,1162]]},{"text":"490","box":[[102,1196],[131,1196],[131,1217],[102,1217]]}],"dimensions":{"height":1247,"width":864}}