{"ocr_results":[{"text":"建國以采（1949--1997)","box":[[88,64],[275,64],[275,84],[88,84]]},{"text":"第三十六章總结一一對文革的簡短","box":[[90,147],[748,147],[748,181],[90,181]]},{"text":"要辞價文革，可以是一件巨的1作，因為文革的發展程是由","box":[[135,246],[747,246],[747,263],[135,263]]},{"text":"很多社管上錯综複雜的矛盾交义而成，往往脱離了統治者预期的道，","box":[[91,281],[745,281],[745,298],[91,298]]},{"text":"然而，假若我們能掌握文革的歷史事實，了解文革爆發的原因，對人民","box":[[90,316],[749,316],[749,333],[90,333]]},{"text":"心熊及社會各方面所带來的影響，還是可以給它作出一點初步的總結及","box":[[88,348],[749,350],[749,370],[88,368]]},{"text":"價的。","box":[[87,385],[170,383],[170,403],[87,406]]},{"text":"對建國後雨條路门争的看法","box":[[147,444],[538,444],[538,467],[147,467]]},{"text":"在中共建國以前，於一九四五年召開的全黛七大會中·已明確制","box":[[133,503],[749,503],[749,523],[133,523]]},{"text":"訂新民主主義路線，容許私有制及其他各種成份的經濟在一段長的时","box":[[89,537],[749,538],[749,558],[89,557]]},{"text":"間保留客，但是中共對蒋介石门爭的迅速勝利，以及一九五三年對資本","box":[[89,574],[749,574],[749,594],[89,594]]},{"text":"生羲工尚業顺利和迅速的改造，皆使極端重視個人理想的毛澤東鼓舞起","box":[[91,611],[748,611],[748,627],[91,627]]},{"text":"来，他坚信意志的力量，為人的力量不單可以推進革命，更能加快社","box":[[90,644],[747,644],[747,661],[90,661]]},{"text":"會發展進程，對經濟规律發號施令，他覺得苦的農民正由於苦所以","box":[[88,678],[748,679],[748,699],[88,698]]},{"text":"蕴藏著·一種極大的社會主義極性，故此，他強調以思想道德鼓的方","box":[[88,713],[748,714],[748,734],[88,733]]},{"text":"法，刺激人民無條件的忘我動，使中國快踏上共產主羲的道路。","box":[[89,751],[732,751],[732,768],[89,768]]},{"text":"然而，随著三面紅旗的失取，全國的大荒，迫使毛澤束不得不接","box":[[133,784],[748,785],[748,805],[133,804]]},{"text":"受現實，而将黛政的實權交予刘少奇等收拾局。在文革期間，劉的","box":[[90,822],[747,822],[747,839],[90,839]]},{"text":"經濟及社會政策成為他們被批判的罪状。当然，在批判者眼中看來，劉","box":[[88,855],[750,856],[750,876],[88,875]]},{"text":"鄱的政策都是鐵案如山的罪狀，可是假如我們将這些罪證和當时所處的","box":[[90,894],[747,894],[747,911],[90,911]]},{"text":"時代背影聯繁起來，就會發現，很多劉提倡的經濟政策都是為了挽救","box":[[87,926],[749,927],[749,947],[87,946]]},{"text":"經濟困境的權宜措施，很多政策都是當時包括毛澤東在内的领導人共同","box":[[88,961],[748,962],[748,982],[88,981]]},{"text":"接受的意見，就算是毛分歧的重點，亦只是雙方對經濟發展的速度及","box":[[88,997],[747,998],[747,1018],[88,1017]]},{"text":"執行方針的不同看法。","box":[[88,1032],[297,1033],[297,1053],[88,1052]]},{"text":"可以说，劉少奇是-一個较為穩健型的社會主羲者，例如，他為農","box":[[133,1068],[748,1070],[748,1090],[133,1088]]},{"text":"業合作化的速度-·定不能推得太快，一定要等待工業現代化和城市能創","box":[[88,1103],[748,1104],[748,1124],[88,1123]]},{"text":"造出较多就業機會以吸纳震村剩餘人手後才能得到震民摊戴，水到渠","box":[[89,1141],[746,1141],[746,1158],[89,1158]]},{"text":"574","box":[[95,1192],[126,1192],[126,1213],[95,1213]]}],"dimensions":{"height":1247,"width":864}}