{"ocr_results":[{"text":"建國以来(1949-1997)","box":[[79,62],[266,62],[266,82],[79,82]]},{"text":"的歷史潮流：群累自發地對穩健派治國路線投下了定的信任票：","box":[[79,145],[702,146],[702,166],[79,165]]},{"text":"四個現代化日，我們一定設酒重祭。群支持穩健派亦可理解為","box":[[125,182],[740,182],[740,202],[125,202]]},{"text":"希望社會上有较大的自由度，脱封建思想拍制。民心所向更加速了極","box":[[80,218],[740,218],[740,238],[80,238]]},{"text":"左派的下台。","box":[[80,253],[203,253],[203,273],[80,273]]},{"text":"天安門事件後，極左派進一步開展更大规模的批連動，傅媒出現","box":[[123,287],[740,287],[740,307],[123,307]]},{"text":"大批極左派觀點之文章，重點在於宣傅黛内有一個資產隋級，亚大批「三","box":[[79,322],[740,323],[740,343],[79,342]]},{"text":"填指示為三株大毒草，亚指出七五年的全面整頓是：","box":[[81,360],[582,360],[582,377],[81,377]]},{"text":"「鄞小平翻案復辟的行動部署。一聲整頓令下，翻案妖風起·..…文","box":[[118,409],[739,411],[739,434],[118,432]]},{"text":"化大革合的成果...··他一律都要整顿·..其實質就是資產级整無產","box":[[80,447],[740,448],[740,468],[80,467]]},{"text":"级，就是資本主義復辟。《六十--","box":[[79,483],[409,485],[409,505],[79,503]]},{"text":"極方派不优要打倒小平，更希望撤換一大批老幹部，他們指出要","box":[[123,536],[739,536],[739,556],[123,556]]},{"text":"特别警惕「中央出修止主羲」，要|一级的一级」，「一直的到中央政治","box":[[81,572],[738,572],[738,589],[81,589]]},{"text":"局。","box":[[80,607],[128,607],[128,624],[80,624]]},{"text":"七六年下旬，中國又出現了其他重大變故及離。首先是七月六日","box":[[126,641],[738,641],[738,661],[126,661]]},{"text":"中國原幻軍總司令、德高望重的人大委員長朱德逝世。七月廿八日，河","box":[[80,676],[740,675],[740,695],[80,696]]},{"text":"北省的唐山地區發生強烈地震·死亡人敷多達數十萬，損失惨重，跟著","box":[[80,712],[740,712],[740,732],[80,732]]},{"text":"四川潘松地區也發生了七级以上地震。","box":[[80,746],[442,747],[442,767],[80,766]]},{"text":"三毛澤東逝世與四人翼的跨台","box":[[79,800],[454,799],[454,823],[79,824]]},{"text":"中共中央主席毛澤東於七六年九月九日去世。毛澤東的逝世使左","box":[[125,855],[739,855],[739,872],[125,872]]},{"text":"派顿失靠山，政治天秤隨即倾斜，缺乏了毛澤東的政治平衡，雙方即時","box":[[80,889],[739,889],[739,909],[80,909]]},{"text":"出現面對面的门爭，矛盾加劇，如箭在弦。十月六日，離毛澤東世不到","box":[[82,925],[738,925],[738,942],[82,942]]},{"text":"一個月，穩健派随即動用非常手段，倚仗軍事力量，逮捕四人，全面","box":[[80,959],[739,959],[739,979],[80,979]]},{"text":"打跨左派力量。","box":[[79,992],[246,994],[246,1015],[79,1013]]},{"text":"早在毛澤東病重期间，穩健派便開始研究以非常手段逮捕極左派，","box":[[124,1031],[735,1031],[735,1048],[124,1048]]},{"text":"王震將軍多次向葉劍英進言：「把四人抓起来穩健派之所以没有這樣","box":[[81,1066],[741,1066],[741,1086],[81,1086]]},{"text":"做，完全是於毛澤東的阻力·在一本由中共中央黛校出版和王震寫序","box":[[79,1101],[740,1100],[740,1120],[79,1121]]},{"text":"的著作《巢劍英在一九七六》中，作者范硕精彩地刻劃出毛澤東逝世前穗","box":[[81,1137],[740,1137],[740,1157],[81,1157]]},{"text":"634","box":[[87,1190],[117,1190],[117,1210],[87,1210]]}],"dimensions":{"height":1247,"width":864}}