{"ocr_results":[{"text":"第三十八章極左派舆穗健派的较量到四人跨台（一九七二一七六）","box":[[264,63],[775,63],[775,80],[264,80]]},{"text":"健派审事首腦的考：","box":[[118,147],[325,147],[325,164],[118,164]]},{"text":"王震在七六年中旬拜會葉劍英，指出天安門的事心不服。韩部和","box":[[161,200],[778,199],[778,219],[161,220]]},{"text":"群恨死那個上海了°』","box":[[115,232],[388,236],[388,259],[115,255]]},{"text":"可是，那綫個人是毛主席點將的呀！葉劍英心裡也恨，只是凝著","box":[[160,269],[778,270],[778,290],[160,289]]},{"text":"毛澤東，觉得難辦。王震再道：為什镶他們這樣猖狂？把他们弄起","box":[[118,307],[777,307],[777,324],[118,324]]},{"text":"来不就解决問題了？了","box":[[117,341],[345,342],[345,360],[117,359]]},{"text":"葉劍英還是不動聲色。停了一會兒，只見他做了一個打谜式的手","box":[[161,376],[778,376],[778,396],[161,396]]},{"text":"势：先伸出左手，握紧拳頭，坚起大拇指，向上晃兩晃，然後把大姆指","box":[[118,413],[777,413],[777,430],[118,430]]},{"text":"倒遍来，往下按了按。","box":[[117,448],[328,448],[328,468],[117,468]]},{"text":"王震住了，這是什意思？業劍英又向他點了點頭。","box":[[161,483],[673,482],[673,502],[161,503]]},{"text":"王震想了想，终於猜明白了：大拇指是指毛主席。他老人家退在","box":[[162,520],[777,520],[777,537],[162,537]]},{"text":"世，不宜輕举妄動，等去世以後再，要等待時機。（六十二)","box":[[116,552],[697,554],[697,574],[116,572]]},{"text":"毛澤東逝世後，氣氛愈加紧张，雙方都抓紧時間下手，最榮臻元師","box":[[165,607],[777,607],[777,624],[165,624]]},{"text":"要杨成武將軍到葉劍英那禅轉告他的話说：「四人·....什魔壤事都能翰","box":[[118,640],[775,640],[775,657],[118,657]]},{"text":"得出来的，要有所警惕，防止他們先下手。如果他們把小平暗害了，把","box":[[117,675],[778,675],[778,695],[117,695]]},{"text":"葉師软禁了，那就嘛了。·..探用万内门爭的正常途径來解决他們的","box":[[118,712],[776,712],[776,729],[118,729]]},{"text":"問题，是無濟於事的。只有我們先下手，探取然措施，才能防止意","box":[[117,747],[776,747],[776,764],[117,764]]},{"text":"外。」（六十三)此外，華國锋及其他高層將领亦表達了同樣意見，故此，","box":[[117,782],[774,782],[774,802],[117,802]]},{"text":"務實派决定以快打慢，馬上行動。","box":[[117,817],[436,817],[436,837],[117,837]]},{"text":"在那遵厢，極左派也大举活動，製造舆，到處串連，向他們控制","box":[[162,854],[776,854],[776,871],[162,871]]},{"text":"的上海民兵突然派發檐枝，亚提出要雞備打仗。極左派亦插手軍隧，「突","box":[[117,889],[776,889],[776,906],[117,906]]},{"text":"然調换了北京郊區某装甲兵部隧的雨個師参長，備随時指坦克車","box":[[118,924],[775,924],[775,941],[118,941]]},{"text":"东南、西北方向開進北京城，造成椅角爽攻之勢。」（注六十四）此外，","box":[[117,958],[774,958],[774,978],[117,978]]},{"text":"1四人帮對奪權上台已經作好全面部署，先由他們掌握的上海和長沙發","box":[[118,995],[777,995],[777,1012],[118,1012]]},{"text":"難，要求打倒華國锋、葉劍英等人，四人在北京馬上動手抓人，亚召","box":[[115,1028],[777,1029],[777,1049],[115,1048]]},{"text":"開十届三中全會，宣布上台。為此，上海的民兵已經武装待命，北京清","box":[[116,1065],[777,1064],[777,1084],[116,1085]]},{"text":"華、北大的民兵也作了動員備，而且北京附近一支部隧的指官也已","box":[[116,1099],[776,1100],[776,1120],[116,1119]]},{"text":"奉命到牌时刻就把坦克開到長安街來收拾局面。」（六十五）","box":[[116,1135],[685,1136],[685,1156],[116,1155]]},{"text":"635","box":[[740,1189],[770,1189],[770,1209],[740,1209]]}],"dimensions":{"height":1247,"width":864}}