{"ocr_results":[{"text":"建圈以来（1949-1997）","box":[[100,81],[285,81],[285,102],[100,102]]},{"text":"黛一專政、維持社會穩定、純潔社會風氣以及反腐败等。","box":[[99,166],[658,165],[659,185],[99,186]]},{"text":"在南巡講話中，部小平提出打擎各種犯罪活動，除各種醜蕊現","box":[[143,201],[760,201],[760,221],[143,221]]},{"text":"象，手软不得。」（注三十六)而在整個改革開放過程中都要反腐，亚将廉","box":[[99,236],[761,235],[761,256],[99,257]]},{"text":"政建設當作大事来處理。","box":[[101,272],[332,272],[332,292],[101,292]]},{"text":"此外，部小平亦提出反對資產臂級自由化要搞二十年，亚指出：","box":[[143,307],[755,307],[755,327],[143,327]]},{"text":"在苗頭出現時不注意，就會出事。）（三十七）","box":[[102,342],[528,344],[528,364],[102,362]]},{"text":"五批政治對手，影馨人事安排","box":[[100,403],[503,403],[503,426],[100,426]]},{"text":"直接批以陳雲為首的經濟進派，及以邺力群為领導的左派理","box":[[144,457],[760,456],[760,476],[144,477]]},{"text":"權威，亚針對中央的高層领導，提出不搞改革開放下台","box":[[100,492],[682,491],[682,511],[100,512]]},{"text":"鄱小平在提出其建國路線後深刻的指出：「正確的政治路線要靠正確","box":[[143,527],[761,526],[761,546],[143,547]]},{"text":"的組織路線來保證。」（三十八)邺以老年人不應阻中央現時领導開展工","box":[[100,561],[762,561],[762,584],[100,584]]},{"text":"作為引子，不點名的批陳雲，務求以直接挑的姿態壓倒經濟進派","box":[[100,597],[761,596],[761,616],[100,617]]},{"text":"的影響力，而有利其在十四大中挑選支持其改革開放路線的领導人。","box":[[100,633],[757,632],[757,652],[100,653]]},{"text":"部小平批陳雲：老年有長處，但也有很大的弱點，容易固執。」（","box":[[103,670],[759,670],[759,687],[103,687]]},{"text":"三十九）绑進而批陳雲不實地考察特區，而站在老遠指手劃。","box":[[101,704],[757,702],[757,723],[101,725]]},{"text":"小平亦批理家力群，政治家宋平及李銘等，他們「拿大帽子","box":[[101,739],[760,738],[760,758],[101,759]]},{"text":"赫唬人！。","box":[[101,774],[191,774],[191,795],[101,795]]},{"text":"在批政治對手後，小平更對中共的最高领導作出必须持改革","box":[[143,811],[760,810],[760,830],[143,831]]},{"text":"期放的要求，他指出「對改革開放熱不熱心，是驗幹部不持社會主","box":[[102,846],[759,845],[759,865],[102,866]]},{"text":"羲道路的最重要的標，其他標不能超越這個標，更不能取代這個","box":[[101,881],[759,880],[759,900],[101,901]]},{"text":"標。持改革開放就上台，不搞改革開放就下台。」（四十》","box":[[102,917],[757,917],[757,937],[102,937]]},{"text":"第四節對徹南巡講話的爭持，以及政治局、","box":[[102,984],[727,986],[727,1013],[102,1012]]},{"text":"人大及政協會的召開","box":[[225,1032],[518,1032],[518,1056],[225,1056]]},{"text":"「左】派理家對南巡講話的抵抗","box":[[162,1101],[557,1101],[557,1124],[162,1124]]},{"text":"小平南巡講話傅返北京後，引起左派理家極度不滿，他們韶為","box":[[145,1156],[758,1156],[758,1177],[145,1177]]},{"text":"930","box":[[109,1210],[138,1210],[138,1231],[109,1231]]}],"dimensions":{"height":1255,"width":878}}