{"ocr_results":[{"text":"第六十二章反腐、反罪总·舆思想道德建設","box":[[422,78],[775,78],[775,96],[422,96]]},{"text":"要整體的较全面的改善中國的社會治安，除中央要持續的推行反腐","box":[[116,159],[776,160],[776,180],[116,179]]},{"text":"贩、「打犯罪，加強政法隧伍建建設外，還必须續推行全民的道德","box":[[115,194],[776,195],[776,215],[115,214]]},{"text":"文化教育、不解推行禁毒禁黄行動、健全法制、加強各项社會保障、遂","box":[[117,230],[776,231],[776,251],[117,250]]},{"text":"步改害政府官員的待遇、強化社會及舆督、完善經濟體制改革、堵","box":[[117,267],[775,267],[775,285],[117,285]]},{"text":"塞各填漏洞，免給握有權力官員可乘之機，這樣才能長遠更根本的改","box":[[116,301],[775,302],[775,322],[116,321]]},{"text":"善中國的社會治安状况。","box":[[116,336],[348,337],[347,358],[116,357]]},{"text":"第三節思想道德建設—一「講政治」到「精","box":[[115,413],[749,415],[749,442],[115,440]]},{"text":"神文明建設」","box":[[236,460],[406,460],[406,487],[236,487]]},{"text":"除進行打及反腐外，為保证乾部及人民有正確的思想，江澤民","box":[[158,525],[775,527],[775,547],[157,545]]},{"text":"在九五年九月底的十四屆五中全會召集人會上，強調「领導乾部--定要","box":[[116,560],[774,562],[774,582],[116,580]]},{"text":"講政治」，而在九六年十月十日的十四届六中全會上，中共央更通遍（中","box":[[117,596],[773,596],[773,616],[117,616]]},{"text":"共中央關於加強社會主義精神文明建設若干重要問题的决》。實際上，","box":[[115,632],[772,633],[772,653],[115,652]]},{"text":"中國政府自五中全會以來曾做了大量工作，包括江澤民多次發表谈","box":[[116,667],[775,668],[775,688],[116,687]]},{"text":"話，通過各種媒發表大量文章，宣傅乾部要講政治及建立精神文","box":[[114,702],[775,703],[775,723],[114,722]]},{"text":"明，此外，中央更树植正氣，宣揚先進事，鞭撻醜惡，揭發壤人壤","box":[[115,737],[775,738],[775,758],[115,757]]},{"text":"事。上述工作皆示中央高層進行思想道德建設的决心。","box":[[116,774],[649,774],[649,794],[116,794]]},{"text":"中共强韩部講政治及建立精神文明的原因","box":[[167,836],[678,837],[678,860],[167,859]]},{"text":"（1）針對韩部政治思想素質下降","box":[[114,895],[436,895],[436,918],[114,918]]},{"text":"适點與中共高層連續出現各種腐現象有直接關系。江澤民曾尖","box":[[158,946],[773,947],[773,967],[157,966]]},{"text":"的批：","box":[[114,981],[195,984],[195,1004],[114,1001]]},{"text":"「有的幹部不讀書，不看報，不研究文件，不調查研究，很少政治","box":[[153,1033],[774,1036],[774,1060],[152,1057]]},{"text":"上觀察形势。有的對万的方針政策和决策，合意的就執行，不合意的就","box":[[114,1070],[774,1073],[774,1093],[114,1090]]},{"text":"不執行，我行我素。為了他那一點局部利益或者個人利益，甚至連犯罪","box":[[115,1105],[774,1107],[774,1127],[115,1125]]},{"text":"的問题都加以保護。有的是非不分，建背的基本路線和政策的錯言","box":[[116,1140],[772,1143],[772,1164],[116,1160]]},{"text":"1097","box":[[729,1207],[765,1207],[765,1227],[729,1227]]}],"dimensions":{"height":1255,"width":878}}