{"ocr_results":[{"text":"第六十四章經濟建设一跨越九七年的經濟持續發展","box":[[373,77],[780,78],[780,99],[373,98]]},{"text":"2.保證農民收入持續增長，要积極發展以農產品加工為主的鄉镇企","box":[[161,163],[779,164],[779,184],[161,183]]},{"text":"業、带動種養業的發展，把生產、加工、銷售聯結·實行貿工農","box":[[189,197],[778,199],[778,219],[189,217]]},{"text":"一體化。","box":[[187,233],[271,233],[271,254],[187,254]]},{"text":".加强水利建設，保證大江大河安全度汛；","box":[[163,270],[572,270],[572,290],[163,290]]},{"text":"1.保持農村社會的穩定，集中解决地方農民負過重的問","box":[[164,304],[779,306],[779,326],[164,324]]},{"text":"题十六","box":[[189,339],[309,343],[308,364],[188,360]]},{"text":"最後，是次會决定為加強震業的地位，應加快農村體制改革步","box":[[162,375],[778,376],[778,396],[162,395]]},{"text":"伐、加大農業技術推廣力度，加強震田水利基本建設，優化農村產業结","box":[[118,410],[778,412],[778,432],[118,430]]},{"text":"構、切實减輕農民負·確保農業增產、農民增收，及農村穩定。","box":[[118,445],[742,448],[742,469],[118,467]]},{"text":"（8）全國金融工作會（九七年一月十三日）","box":[[118,500],[556,501],[556,522],[118,521]]},{"text":"全國金融會提出九七年的金融工作應續推行適度繁的貨政","box":[[166,551],[778,553],[778,573],[166,571]]},{"text":"策，整顿金融秩序，防亚化解金融風，深化金融改革·亚配合國家","box":[[117,587],[778,589],[778,609],[117,607]]},{"text":"經濟及產业政策，慎重處理贷款的投放方向，支持有效益的企業，亚協","box":[[118,622],[778,625],[778,645],[118,643]]},{"text":"助克服各地方低水平重複建設問題，以促進經濟結構的調整。","box":[[118,658],[697,660],[697,680],[118,678]]},{"text":"在金融會進行期間，中國四大國有商業銀行（中國農業銀行、中國","box":[[163,693],[777,695],[777,715],[163,713]]},{"text":"銀行、中國工商銀行和中國建設銀行）皆召開各銀行的全國分行行長會","box":[[117,728],[777,730],[777,750],[117,748]]},{"text":"·些銀行將據全國金融會的總體精神，分别制定九七年信貨工作","box":[[117,763],[776,765],[776,785],[117,783]]},{"text":"的方针。","box":[[116,798],[199,801],[199,822],[116,819]]},{"text":"例來说：中國銀行决定九七年信贷方向應支持有信警的國有進出","box":[[163,835],[776,837],[776,858],[163,856]]},{"text":"口企，以發展有效益、有市場的進出口業務；支持國有大型企業發","box":[[118,871],[777,873],[777,893],[118,891]]},{"text":"展：禁對盲目競爭、没有效益、挪用銀行资金的企業贷款；支持國家","box":[[116,906],[778,907],[778,927],[116,926]]},{"text":"重點项目，限制重複建設，無市場前景、缺乏資本金的固定資產投資；","box":[[117,941],[773,942],[773,962],[117,961]]},{"text":"及支持高利税、高創匯、高銷售额的外商投資企業等。（言“1七）","box":[[118,975],[719,980],[718,1001],[118,997]]},{"text":"（9）八属人大第五年會（一九九七年三月）","box":[[118,1032],[552,1032],[552,1052],[118,1052]]},{"text":"在是次人大會的政府工作報告中，總理李鹏花了相當大的篇幅，","box":[[162,1083],[773,1084],[773,1104],[162,1103]]},{"text":"關述网有企業的改革，他提出了推進國企改革的六大措施，分别為集中","box":[[117,1117],[775,1118],[775,1138],[117,1137]]},{"text":"力量抓好大型企業和企業集團；進一步放活國有小企業；规破產，鼓","box":[[118,1153],[775,1154],[775,1175],[118,1174]]},{"text":"1157","box":[[731,1211],[766,1211],[766,1230],[731,1230]]}],"dimensions":{"height":1255,"width":878}}