{"ocr_results":[{"text":"第六十五章香港前途問题舆一國兩制","box":[[483,77],[765,77],[765,92],[483,92]]},{"text":"方關係]及「香港社會内部矛盾」，而制定整個基本法的過程，實際都是圍","box":[[105,159],[767,157],[767,177],[105,179]]},{"text":"這兩個重心作出讨。","box":[[105,194],[339,193],[339,213],[105,214]]},{"text":"（2）中央舆地方關係","box":[[105,243],[307,243],[307,263],[105,263]]},{"text":"在制定基本法的遍程中，由於中央政府整守一國兩制的國策，亚以","box":[[150,288],[765,287],[765,305],[150,306]]},{"text":"開放寬的熊度靈活地處理中港關係，中共將可以下放的權力盏量下放","box":[[108,324],[766,324],[766,341],[108,341]]},{"text":"予港人，故與中央與地方關係有關的條文普遍為香港人，甚至國際社會","box":[[108,357],[766,356],[766,376],[108,377]]},{"text":"（包括英國）的接受。草委會在八八年中下旬第一次港人意見後，将","box":[[112,394],[767,394],[767,411],[112,411]]},{"text":"備受港人關注的有關中央與地方之條文大幅修改，深受港人截迎。","box":[[107,429],[727,428],[727,446],[107,448]]},{"text":"當時曾参與探訪基本法起草過程的記者事後回憶：在中央特區組内","box":[[150,465],[765,464],[765,482],[150,483]]},{"text":"最大的反對派在小组會後也喜形於色，然他多次提出的内部繁急","box":[[108,501],[764,501],[764,518],[108,518]]},{"text":"條款始终未為小组讨，但他也對小组的成果感到滿意，他喜孜孜地對","box":[[107,536],[766,536],[766,553],[107,553]]},{"text":"記者，在中央舆特區係的重要條文上，中央下放了很多權力給特","box":[[107,571],[765,571],[765,588],[107,588]]},{"text":"區，此經驗顯示，對香港有利的事，港人應量爭取。（大略）（三十）","box":[[105,604],[764,605],[764,625],[105,624]]},{"text":"上迹港入的反應可證，中央政府希望将可以下放的權力交予香港，","box":[[108,642],[763,642],[763,659],[108,659]]},{"text":"而中方的主要制約，乃是需要考中國境内其他省市及人民之接受程","box":[[109,678],[765,678],[765,695],[109,695]]},{"text":"度，亦是-一國兩制中一國的原则。","box":[[108,714],[468,714],[468,731],[108,731]]},{"text":"基本法在九零年通過之前，經歷了令香港人震的八九民連及六四","box":[[151,748],[764,748],[764,765],[151,765]]},{"text":"事件，香港出現了移民潮，社會亚普遍蔓中方干预香港内部事務的可","box":[[107,783],[766,782],[766,802],[107,803]]},{"text":"能性·而在另：·方面，中國政府指出中央根本未改變對港政策，但亦","box":[[108,820],[766,820],[766,837],[108,837]]},{"text":"批香港市民投身及以财政支持北京學連乃是干预中國内部事務，建反","box":[[108,855],[766,855],[766,872],[108,872]]},{"text":"一國兩制的原则，故此，在基本法條文上加强了對香港的限制，目的在","box":[[108,891],[766,891],[766,908],[108,908]]},{"text":"防止香港将来再1干预大陵的事務。然而，假若分析基本法最後通過有","box":[[108,926],[765,926],[765,943],[108,943]]},{"text":"關颠覆及禁止與外國政治组織聯紧（這類條文在香港過往-直存在）的條","box":[[108,961],[766,961],[766,978],[108,978]]},{"text":"文，皆可發覺中央容香港自行立法加以禁止，将處理此等事件的主勤","box":[[108,997],[765,997],[765,1014],[108,1014]]},{"text":"權交予香港，使大隆干预香港事務的機會大大降低。","box":[[108,1032],[600,1032],[600,1049],[108,1049]]},{"text":"另一個引起港人懷疑之例子是基本法第十八條有關繁急状態下」中","box":[[151,1068],[766,1068],[766,1085],[151,1085]]},{"text":"國可将全國性法律引人香港，若细心分析，此條文將香港的動凯明確介","box":[[108,1103],[764,1103],[764,1120],[108,1120]]},{"text":"定為香港政府「不能控制的危及國家統一或安全的動」，表明中央政府","box":[[109,1138],[764,1138],[764,1155],[109,1155]]},{"text":"1177","box":[[720,1204],[758,1204],[758,1224],[720,1224]]}],"dimensions":{"height":1255,"width":878}}