{"ocr_results":[{"text":"第六十七章開放十九年的經濟體制改革與經濟發展述评","box":[[352,79],[776,79],[776,97],[352,97]]},{"text":"四","box":[[117,162],[172,162],[172,183],[117,183]]},{"text":"經改需要相對寬的環境，慎重處理|改革」與「調","box":[[165,162],[775,161],[775,182],[165,183]]},{"text":"整的關係，遍就需要持抑制通貨膨胀的戴略方針","box":[[172,203],[773,203],[773,223],[172,223]]},{"text":"（1）經濟改革需要一個宽的經濟環境","box":[[121,260],[515,260],[515,281],[121,281]]},{"text":"要發市場調配資源之功能，除邵要有價格、企改及政府功能轉换","box":[[162,314],[773,314],[773,331],[162,331]]},{"text":"等因素外，需要有一個寬的經濟環境，具體表現為出現一個買方市","box":[[116,348],[774,348],[774,368],[116,368]]},{"text":"場（供大於求）：因為只有買方币場的存在，才能促使企業間爭，迫使","box":[[116,385],[773,385],[773,402],[116,402]]},{"text":"企業精打細算、提高效率、改善經營，不再出現像賣方市場時商品像皇","box":[[116,419],[774,419],[774,439],[116,439]]},{"text":"帝女兒不愁嫁的情况。","box":[[115,455],[325,455],[325,475],[115,475]]},{"text":"改革時的寬環境包括國家摊有较充裕之财力，价格改革普遍會","box":[[158,489],[774,490],[774,510],[157,509]]},{"text":"将以往不合理的產品低價格情况改變，物價上升成為價改初期之產物。","box":[[114,524],[771,525],[771,545],[114,544]]},{"text":"為保證企業及個人收入不會受價格上調之影響，除要求企業及個人承","box":[[115,559],[775,560],[775,580],[115,579]]},{"text":"及消化部分提價外，國家需有相對充實的财力對在價改中損失利益","box":[[114,595],[774,596],[774,616],[114,615]]},{"text":"的個人舆單位作出補贴，以消除不满，缓和改革之陣痛。","box":[[115,631],[652,632],[652,653],[115,652]]},{"text":"故此，在改革前：國家應量抑制過份張之投資及消費，亚以產","box":[[158,667],[774,668],[774,688],[157,687]]},{"text":"業、财政、貨等政策保持總供需的基本平衡，阻止賣方市場及通之","box":[[114,702],[773,704],[773,724],[114,722]]},{"text":"出現·創造寬環境·大幅降低改革離度。","box":[[116,738],[522,738],[522,758],[116,758]]},{"text":"（2）「九五期間诱發通服的因素","box":[[119,790],[443,792],[443,814],[119,811]]},{"text":"這理就涉及-個抑制通貨膨及保持宏觀經濟穩定的大問題。累所","box":[[157,843],[774,844],[774,864],[156,863]]},{"text":"周知，在任何國家，通都是經濟健康成長的大，中國在「九五計劃」","box":[[115,878],[772,880],[772,900],[115,898]]},{"text":"期間正處於經濟體制轉軌和快速增長時期，發通服的因素十分多，這","box":[[114,913],[774,915],[774,936],[114,934]]},{"text":"分别包括：","box":[[114,949],[217,949],[217,970],[114,970]]},{"text":"1.趟往巍年通胀幅度大，横累起来的通服力较重，如九四年寫","box":[[159,999],[771,999],[771,1016],[159,1016]]},{"text":"百分之廿一點七：九五年為百分之十四點八，在高起點的通基","box":[[185,1032],[773,1033],[773,1053],[185,1052]]},{"text":"键上增大了保持物價穩定的難度。","box":[[185,1069],[502,1069],[502,1086],[185,1086]]},{"text":"2.為理顺價格，改變部分晨產品、基產品及生產要素价格偏低的","box":[[156,1115],[770,1115],[770,1132],[156,1132]]},{"text":"情况，必需進行价格調整，價格改革將通過成本推動，引起全國","box":[[184,1148],[769,1149],[769,1170],[184,1169]]},{"text":"1257","box":[[727,1208],[764,1208],[764,1228],[727,1228]]}],"dimensions":{"height":1255,"width":878}}