{"ocr_results":[{"text":"第六十八章建國方略一一官方與民間","box":[[481,79],[766,80],[766,101],[481,100]]},{"text":"力，以對政府工作進行督。推行差额選制度，使民主能遂步落實。","box":[[106,162],[761,164],[761,184],[106,182]]},{"text":"7.強調法制","box":[[148,220],[265,220],[265,241],[148,241]]},{"text":"加強法制建設、立法工作及執法力度·保障司法機構能獨立行使","box":[[149,269],[766,272],[766,292],[149,290]]},{"text":"權，亚提高公民的法律意識，中國更出現多宗市民或民間團體向政府提","box":[[104,305],[764,307],[764,327],[104,325]]},{"text":"出的案件。","box":[[106,341],[250,341],[250,361],[106,361]]},{"text":"（2）整舆反腐败","box":[[105,395],[283,395],[283,416],[105,416]]},{"text":"進行整黛，以克服部分黛員以權谋私、奢侈浪费及食污腐化的現","box":[[147,446],[765,449],[765,469],[147,467]]},{"text":"象，中央制定格的紀律，對犯錯的員幹部進行教育，以及對腐分子","box":[[104,482],[764,484],[764,504],[104,502]]},{"text":"執行開除出黛及交法律制裁","box":[[103,517],[379,519],[379,539],[103,537]]},{"text":"（3）國防现代化","box":[[103,572],[256,572],[256,592],[103,592]]},{"text":"重視國防建設，發展國防科技，精兵簡政，紀律明，而提高部","box":[[148,622],[764,625],[764,645],[148,643]]},{"text":"隧之载门力。","box":[[104,657],[228,657],[228,678],[104,678]]},{"text":"二經濟","box":[[100,723],[209,720],[210,749],[101,752]]},{"text":"（1）發展之目標","box":[[103,780],[256,780],[256,801],[103,801]]},{"text":"一-九八二年中共十二大提出徙一九八一年到本世紀末的二十年，經","box":[[148,830],[763,833],[763,853],[148,850]]},{"text":"濟建設總的目標是力爭使全國工震業的總產值翻兩番，即由八零年的七","box":[[103,866],[763,869],[763,889],[103,886]]},{"text":"千-一百億元增加到二零零零年的二萬八千億元，經濟建設略步是在","box":[[103,901],[762,904],[762,925],[103,922]]},{"text":"二十年分兩步走，前十年是打基，积聚力量，創造條件，後十年進入","box":[[103,936],[762,939],[762,959],[103,956]]},{"text":"新的經濟振興時期。（十五)一-九八七年的中共十三大中，總書記趙紫陽","box":[[102,971],[762,973],[762,995],[102,993]]},{"text":"補充提出經濟發展目標的「第三步，到下世紀中葉，人均國民生產總值達","box":[[102,1008],[761,1010],[761,1030],[102,1028]]},{"text":"到中等發達國家水平，人民生活比较富裕，基本實現現代化。」（主十六）","box":[[101,1042],[759,1046],[759,1067],[101,1063]]},{"text":"而在九六年三月就九五計劃（一九九六至二零零零年）及二零--零年遠景","box":[[102,1079],[762,1082],[762,1102],[102,1099]]},{"text":"目標要的報告中，總理李鹏提出在二零零零年在人口比一九八零年增","box":[[102,1114],[760,1117],[760,1137],[102,1134]]},{"text":"長約三億的情况下，實現「人均」國民生產總值比一九八零年翻兩翻，基","box":[[102,1149],[761,1152],[761,1173],[102,1169]]},{"text":"1285","box":[[715,1210],[752,1210],[752,1230],[715,1230]]}],"dimensions":{"height":1255,"width":878}}