{"ocr_results":[{"text":"第六十八章建國方略一一官方舆民間","box":[[499,77],[781,77],[781,95],[499,95]]},{"text":"想，這對中國正在轉變而意識形熊開始散的形勢，極可能帶來更多不","box":[[123,161],[781,161],[781,178],[123,178]]},{"text":"穩定因素。在上述種種衡擎下，加上波蘭團结工會連動的啟示，邺小平","box":[[124,197],[781,197],[781,214],[124,214]]},{"text":"感覺民間及黛内的回應有可能使中國出現混，為維護的權威，在八","box":[[124,233],[780,233],[780,250],[124,250]]},{"text":"零年民八-年初，他開始禁止民刊出版，取缔民間组織亚对<苦戀>開展","box":[[124,268],[781,268],[781,286],[124,286]]},{"text":"批判，而他亦肯定毛澤東思想的歷史地位，這臂段的民主蓮動由於官方","box":[[123,303],[780,303],[780,323],[123,323]]},{"text":"的取缔而正式結束。","box":[[123,339],[313,339],[313,359],[123,359]]},{"text":"（2）重視|雙百方針到反精神污染）","box":[[128,393],[498,392],[498,412],[128,413]]},{"text":"八二年下句中共十二大召開，在官方開放言如尊重知識分子、重","box":[[170,443],[783,443],[783,464],[170,464]]},{"text":"提百花放、百家爭的「雙百方針下，中國大陵一些高級知識分子及","box":[[122,479],[781,480],[781,498],[122,497]]},{"text":"教育文化界的開明韩部如周揚、王若水及于浩成等，開展了對社會主羲","box":[[122,513],[782,514],[782,535],[122,534]]},{"text":"翼化問題的讨，由於這些理有著止統馬克思王羲著作為依據，亚挑","box":[[124,552],[781,552],[781,569],[124,569]]},{"text":"截著万的權威，超過官方的容忍界限，而小平及一些强調黛權和掌管","box":[[124,587],[781,587],[781,604],[124,604]]},{"text":"意識形熊的幹部如邺力群、熊復及贺敬之等亦開展了對這些「精神污染」","box":[[122,621],[781,620],[781,641],[122,642]]},{"text":"理進行批。然而，由於胡耀邦及趙紫陽努力，使反精神污染的連動","box":[[122,656],[781,657],[781,677],[122,676]]},{"text":"只進行了八十二大。","box":[[125,694],[310,694],[310,711],[125,711]]},{"text":"（3）政治改革舆胡耀邦下台","box":[[121,746],[393,745],[393,766],[121,767]]},{"text":"一九八六年中開始，随著經改的深入带來了政制改革的呼聲，在","box":[[174,799],[781,799],[781,817],[174,817]]},{"text":"小平、胡耀邦及萬里等中央领導的支持下，政治改革提上日程，引發思","box":[[125,835],[780,835],[780,852],[125,852]]},{"text":"想大解放及民主瓣學的推行，大陵的思想學术界更出現了寬、和的","box":[[122,868],[781,869],[781,889],[122,888]]},{"text":"環境，很多高級知藏分子如方之、温元凯、蘇绍智、李澤厚、劉寶雁","box":[[123,906],[780,906],[780,923],[123,923]]},{"text":"及王若望等發表很多时局的言。在開放環境下，刺激著各地學生","box":[[124,941],[779,941],[779,958],[124,958]]},{"text":"争取民主的要求，形成八六年底大模的學生連勤。在此情况下，方","box":[[124,977],[780,977],[780,995],[124,995]]},{"text":"之、王若望及劉寶雁由於曾發表尖批辞黛领導的言，而被小平勒","box":[[123,1013],[780,1013],[780,1030],[123,1030]]},{"text":"令開除出黛，開明的胡耀邦也因為對學連及之前的大言探取容忍的","box":[[124,1048],[780,1048],[780,1065],[124,1065]]},{"text":"度被批判而黯然下台，而中共亦開展反自由化遵動。自由化連動由放","box":[[123,1083],[780,1083],[780,1100],[123,1100]]},{"text":"受到代總書記趙紫阳的限制，小平亦不希望此政治震衡擎太大，故","box":[[123,1118],[780,1118],[780,1135],[123,1135]]},{"text":"對反自由化的措施作出格的限制，不致大為另一次政治運動。","box":[[121,1150],[742,1151],[742,1173],[121,1172]]},{"text":"1303","box":[[735,1208],[772,1208],[772,1228],[735,1228]]}],"dimensions":{"height":1255,"width":878}}